control_bytetx.v
module control_bytetx(
    input clk,
    input rst,
    input [7:0] data_in,
    input start,
    output reg done,
    output reg busy,
    output reg tx
);

parameter CLKS_PER_BIT = 4;

reg next_busy;
reg [1:0] state, next_state;
reg [7:0] shift_reg, next_shift_reg;
reg [3:0] bit_count, next_bit_count;
reg [2:0] tick_cnt, next_tick_cnt;

parameter S_IDLE = 2'b00;
parameter S_LOAD = 2'b01;
parameter S_BIT_HOLD = 2'b10;
parameter S_DONE = 2'b11;

always @(posedge clk or posedge rst) begin
        if (rst) begin
            state <= S_IDLE;
            bit_count <= 4'd0;
            tick_cnt <= 3'd0;
            shift_reg <= 8'd0;
        end
        else begin
            state <= next_state;
            bit_count <= next_bit_count;
            tick_cnt <= next_tick_cnt;
            shift_reg <= next_shift_reg;
            busy <= next_busy;
        end
    end

always @(*) begin
    next_state = state;
    done = 1'b0;
    next_busy = busy;
    tx = 1'b1;
    next_bit_count = bit_count;
    next_tick_cnt = tick_cnt;
    next_shift_reg = shift_reg;

    case (state)

        S_IDLE:
        begin
            done = 1'b0;
        if (start) begin
            next_state = S_LOAD;
        end
        else begin
            busy = 1'b0;
            tx = 1'b1;
            next_state = S_IDLE;
        end
        end

        S_LOAD:
        begin
            next_busy = 1'b1;
            next_bit_count = 4'd0;
            next_tick_cnt = 3'd0;
            next_shift_reg = data_in;
            next_state = S_BIT_HOLD;    
        end 

        S_BIT_HOLD:
        begin
            tx = shift_reg[0];
            if (tick_cnt != CLKS_PER_BIT - 1)
            begin
                next_tick_cnt = tick_cnt + 3'd1;
                next_state = S_BIT_HOLD;
            end
            else
                if (bit_count == 7)
                begin
                    next_state = S_DONE;
                end
                else
                begin
                    next_bit_count = bit_count + 4'd1;
                    next_shift_reg = {1'b0, shift_reg[7:1]};
                    next_tick_cnt = 3'd0;
                    next_state = S_BIT_HOLD;
                end
        end
        

        S_DONE: 
        begin
            done = 1'b1;
            next_state = S_IDLE;
            next_busy = 1'b0;
        end

        default:
        begin
            next_state = S_IDLE;
        end
    endcase
end



endmodule

tb_bytetx.v
`timescale 1ns/1ns
`include "control_bytetx.v"

module tb_bytetx;

  parameter CLKS_PER_BIT = 4;

  reg        clk, rst;
  reg  [7:0] data_in;
  reg        start;
  wire       done, busy, tx;

  integer    errors;
  reg  [7:0] recibido;
  integer    k;

  control_bytetx dut (
    .clk(clk), .rst(rst),
    .data_in(data_in), .start(start),
    .done(done), .busy(busy), .tx(tx)
  );

  always begin
    clk = 1; #5;
    clk = 0; #5;
  end

  task enviar(input [7:0] dato);
    begin
      @(negedge clk);
      data_in = dato;
      start   = 1'b1;
      @(negedge clk);
      start   = 1'b0;

      wait (busy);
      @(negedge clk);

      for (k = 0; k < 8; k = k + 1) begin
        repeat (CLKS_PER_BIT/2) @(negedge clk);
        recibido[k] = tx;
        repeat (CLKS_PER_BIT - CLKS_PER_BIT/2) @(negedge clk);
      end

      wait (done);

      if (recibido !== dato) begin
        $display("ERROR t=%0t: envie %b, recibi %b", $time, dato, recibido);
        errors = errors + 1;
      end
      else
        $display("OK t=%0t: %b transmitido correctamente", $time, dato);
    end
 endtask

  initial begin
    $dumpfile("bytetx.vcd");
    $dumpvars(0, tb_bytetx);

    errors  = 0;
    start   = 1'b0;
    data_in = 8'h00;

    rst = 1; #12;
    rst = 0; #20;

    enviar(8'b1010_0101);
    #30;
    enviar(8'b1111_0000);
    #30;
    enviar(8'b0000_0001);

    #50;
    $display("--- terminado con %0d errores ---", errors);
    $finish;
  end

endmodule

bytetx.vcd
$date
	Wed Sep 16 15:27:23 2026
$end
$version
	Icarus Verilog
$end
$timescale
	1ns
$end
$scope module tb_bytetx $end
$var wire 1 ! tx $end
$var wire 1 " done $end
$var wire 1 # busy $end
$var parameter 32 $ CLKS_PER_BIT $end
$var reg 1 % clk $end
$var reg 8 & data_in [7:0] $end
$var reg 8 ' recibido [7:0] $end
$var reg 1 ( rst $end
$var reg 1 ) start $end
$var integer 32 * errors [31:0] $end
$var integer 32 + k [31:0] $end
$scope module dut $end
$var wire 1 % clk $end
$var wire 8 , data_in [7:0] $end
$var wire 1 ( rst $end
$var wire 1 ) start $end
$var parameter 32 - CLKS_PER_BIT $end
$var parameter 2 . S_BIT_HOLD $end
$var parameter 2 / S_DONE $end
$var parameter 2 0 S_IDLE $end
$var parameter 2 1 S_LOAD $end
$var reg 4 2 bit_count [3:0] $end
$var reg 1 # busy $end
$var reg 1 " done $end
$var reg 4 3 next_bit_count [3:0] $end
$var reg 1 4 next_busy $end
$var reg 8 5 next_shift_reg [7:0] $end
$var reg 2 6 next_state [1:0] $end
$var reg 3 7 next_tick_cnt [2:0] $end
$var reg 8 8 shift_reg [7:0] $end
$var reg 2 9 state [1:0] $end
$var reg 3 : tick_cnt [2:0] $end
$var reg 1 ! tx $end
$upscope $end
$scope task enviar $end
$var reg 8 ; dato [7:0] $end
$upscope $end
$upscope $end
$enddefinitions $end
$comment Show the parameter values. $end
$dumpall
b1 1
b0 0
b11 /
b10 .
b100 -
b100 $
$end
#0
$dumpvars
bx ;
b0 :
b0 9
b0 8
b0 7
b0 6
b0 5
x4
b0 3
b0 2
b0 ,
bx +
b0 *
0)
1(
bx '
b0 &
1%
0#
0"
1!
$end
#5
0%
#10
1%
#12
0(
#15
0%
#20
0#
1%
#25
0%
#30
0#
1%
#32
b10100101 ;
#35
b1 6
04
1)
b10100101 &
b10100101 ,
0%
#40
b10 6
b10100101 5
14
b1 9
1%
#45
b10100101 5
14
b10 6
0)
0%
#50
b1 7
1#
b10100101 8
b10 9
1%
#55
b0 +
0%
#60
b10 7
b1 :
1%
#65
0%
#70
b11 7
b10 :
1%
#75
bx1 '
0%
#80
b0 7
b1010010 5
b1 3
b11 :
1%
#85
0%
#90
b1 7
0!
b1010010 8
b0 :
b1 2
1%
#95
b1 +
0%
#100
b10 7
0!
b1 :
1%
#105
0%
#110
b11 7
0!
b10 :
1%
#115
bx01 '
0%
#120
b0 7
b101001 5
b10 3
0!
b11 :
1%
#125
0%
#130
b1 7
1!
b101001 8
b0 :
b10 2
1%
#135
b10 +
0%
#140
b10 7
b1 :
1%
#145
0%
#150
b11 7
b10 :
1%
#155
bx101 '
0%
#160
b0 7
b10100 5
b11 3
b11 :
1%
#165
0%
#170
b1 7
0!
b10100 8
b0 :
b11 2
1%
#175
b11 +
0%
#180
b10 7
0!
b1 :
1%
#185
0%
#190
b11 7
0!
b10 :
1%
#195
bx0101 '
0%
#200
b0 7
b1010 5
b100 3
0!
b11 :
1%
#205
0%
#210
b1 7
0!
b1010 8
b0 :
b100 2
1%
#215
b100 +
0%
#220
b10 7
0!
b1 :
1%
#225
0%
#230
b11 7
0!
b10 :
1%
#235
bx00101 '
0%
#240
b0 7
b101 5
b101 3
0!
b11 :
1%
#245
0%
#250
b1 7
1!
b101 8
b0 :
b101 2
1%
#255
b101 +
0%
#260
b10 7
b1 :
1%
#265
0%
#270
b11 7
b10 :
1%
#275
bx100101 '
0%
#280
b0 7
b10 5
b110 3
b11 :
1%
#285
0%
#290
b1 7
0!
b10 8
b0 :
b110 2
1%
#295
b110 +
0%
#300
b10 7
0!
b1 :
1%
#305
0%
#310
b11 7
0!
b10 :
1%
#315
bx0100101 '
0%
#320
b0 7
b1 5
b111 3
0!
b11 :
1%
#325
0%
#330
b1 7
1!
b1 8
b0 :
b111 2
1%
#335
b111 +
0%
#340
b10 7
b1 :
1%
#345
0%
#350
b11 7
b10 :
1%
#355
b10100101 '
0%
#360
b11 6
b11 :
1%
#365
0%
#370
04
b0 6
1"
b11 9
1%
#375
b1000 +
0%
#380
0"
0#
b0 9
1%
#385
0%
#390
1%
#395
0%
#400
1%
#405
b1 6
1)
b11110000 &
b11110000 ,
0%
b11110000 ;
#410
b10 6
b11110000 5
b0 7
b0 3
14
b1 9
1%
#415
b11110000 5
b0 7
b0 3
14
b10 6
0)
0%
#420
b1 7
0!
1#
b11110000 8
b0 :
b0 2
b10 9
1%
#425
b0 +
0%
#430
b10 7
0!
b1 :
1%
#435
0%
#440
b11 7
0!
b10 :
1%
#445
b10100100 '
0%
#450
b0 7
b1111000 5
b1 3
0!
b11 :
1%
#455
0%
#460
b1 7
0!
b1111000 8
b0 :
b1 2
1%
#465
b1 +
0%
#470
b10 7
0!
b1 :
1%
#475
0%
#480
b11 7
0!
b10 :
1%
#485
0%
#490
b0 7
b111100 5
b10 3
0!
b11 :
1%
#495
0%
#500
b1 7
0!
b111100 8
b0 :
b10 2
1%
#505
b10 +
0%
#510
b10 7
0!
b1 :
1%
#515
0%
#520
b11 7
0!
b10 :
1%
#525
b10100000 '
0%
#530
b0 7
b11110 5
b11 3
0!
b11 :
1%
#535
0%
#540
b1 7
0!
b11110 8
b0 :
b11 2
1%
#545
b11 +
0%
#550
b10 7
0!
b1 :
1%
#555
0%
#560
b11 7
0!
b10 :
1%
#565
0%
#570
b0 7
b1111 5
b100 3
0!
b11 :
1%
#575
0%
#580
b1 7
1!
b1111 8
b0 :
b100 2
1%
#585
b100 +
0%
#590
b10 7
b1 :
1%
#595
0%
#600
b11 7
b10 :
1%
#605
b10110000 '
0%
#610
b0 7
b111 5
b101 3
b11 :
1%
#615
0%
#620
b1 7
b111 8
b0 :
b101 2
1%
#625
b101 +
0%
#630
b10 7
b1 :
1%
#635
0%
#640
b11 7
b10 :
1%
#645
0%
#650
b0 7
b11 5
b110 3
b11 :
1%
#655
0%
#660
b1 7
b11 8
b0 :
b110 2
1%
#665
b110 +
0%
#670
b10 7
b1 :
1%
#675
0%
#680
b11 7
b10 :
1%
#685
b11110000 '
0%
#690
b0 7
b1 5
b111 3
b11 :
1%
#695
0%
#700
b1 7
b1 8
b0 :
b111 2
1%
#705
b111 +
0%
#710
b10 7
b1 :
1%
#715
0%
#720
b11 7
b10 :
1%
#725
0%
#730
b11 6
b11 :
1%
#735
0%
#740
04
b0 6
1"
b11 9
1%
#745
b1000 +
0%
#750
0"
0#
b0 9
1%
#755
0%
#760
1%
#765
0%
#770
1%
#775
b1 6
1)
b1 &
b1 ,
0%
b1 ;
#780
b10 6
b0 7
b0 3
14
b1 9
1%
#785
b0 7
b0 3
14
b10 6
0)
0%
#790
b1 7
1#
b0 :
b0 2
b10 9
1%
#795
b0 +
0%
#800
b10 7
b1 :
1%
#805
0%
#810
b11 7
b10 :
1%
#815
b11110001 '
0%
#820
b0 7
b0 5
b1 3
b11 :
1%
#825
0%
#830
b1 7
0!
b0 8
b0 :
b1 2
1%
#835
b1 +
0%
#840
b10 7
0!
b1 :
1%
#845
0%
#850
b11 7
0!
b10 :
1%
#855
0%
#860
b0 7
b10 3
0!
b11 :
1%
#865
0%
#870
b1 7
0!
b0 :
b10 2
1%
#875
b10 +
0%
#880
b10 7
0!
b1 :
1%
#885
0%
#890
b11 7
0!
b10 :
1%
#895
0%
#900
b0 7
b11 3
0!
b11 :
1%
#905
0%
#910
b1 7
0!
b0 :
b11 2
1%
#915
b11 +
0%
#920
b10 7
0!
b1 :
1%
#925
0%
#930
b11 7
0!
b10 :
1%
#935
0%
#940
b0 7
b100 3
0!
b11 :
1%
#945
0%
#950
b1 7
0!
b0 :
b100 2
1%
#955
b100 +
0%
#960
b10 7
0!
b1 :
1%
#965
0%
#970
b11 7
0!
b10 :
1%
#975
b11100001 '
0%
#980
b0 7
b101 3
0!
b11 :
1%
#985
0%
#990
b1 7
0!
b0 :
b101 2
1%
#995
b101 +
0%
#1000
b10 7
0!
b1 :
1%
#1005
0%
#1010
b11 7
0!
b10 :
1%
#1015
b11000001 '
0%
#1020
b0 7
b110 3
0!
b11 :
1%
#1025
0%
#1030
b1 7
0!
b0 :
b110 2
1%
#1035
b110 +
0%
#1040
b10 7
0!
b1 :
1%
#1045
0%
#1050
b11 7
0!
b10 :
1%
#1055
b10000001 '
0%
#1060
b0 7
b111 3
0!
b11 :
1%
#1065
0%
#1070
b1 7
0!
b0 :
b111 2
1%
#1075
b111 +
0%
#1080
b10 7
0!
b1 :
1%
#1085
0%
#1090
b11 7
0!
b10 :
1%
#1095
b1 '
0%
#1100
b11 6
0!
b11 :
1%
#1105
0%
#1110
04
b0 6
1"
1!
b11 9
1%
#1115
b1000 +
0%
#1120
0"
0#
b0 9
1%
