stoplight.v
module stoplight(
    input clk,
    input rst,
    output red,
    output yellow,
    output green,
    output reg [2:0] counter 
);


reg [1:0] state, next_state;
reg [2:0] next_counter; //Declaramos un contador que transfiere la información del contador actual al siguien estado por cada flanco

parameter S0 = 2'b00; // Green
parameter S1 = 2'b01; // Yellow_1
parameter S2 = 2'b10; // Red
parameter S3 = 2'b11; // Yellow_2

always @(posedge clk or posedge rst) begin
    if (rst) begin
        state <= S0;
        counter <= 3'd0;
    end
    else begin
        state <= next_state;
        counter <= next_counter;
    end
end

always @(*) begin
    next_state = state; //Cambios en state o counter activan la lógica combinacional
    next_counter = counter + 3'd1; //Al activar la lógica combinacional, el contador se incrementa en 1, para que al siguiente flanco, se haga este incremento

    case (state)
        S0: begin
            if (counter == 3'd4) begin 
                next_state = S1;
                next_counter = 3'd0;
            end
            else begin
                next_state = S0;
            end
        end
        S1: begin
            if (counter == 3'd1) begin
                next_state = S2;
                next_counter = 3'd0;
            end
            else begin
                next_state = S1;
            end
        end
        S2: begin
            if (counter == 3'd3) begin
                next_state = S3;
                next_counter = 3'd0;
            end
            else begin
                next_state = S2;
            end
        end
        S3: begin
            if (counter == 3'd1) begin
                next_state = S0;
                next_counter = 3'd0;
            end
            else begin
                next_state = S3;
            end
        end
        default begin
            next_state = S0;
            next_counter = 3'd0;
        end
    endcase


end

assign red = (state == S2);
assign yellow = (state == S1) || (state == S3);
assign green = (state == S0);


endmodule

tb_stoplight.v
`timescale 1ns/1ns
`include "stoplight.v"



module tb_stoplight;

  reg clk, rst;
  wire red, yellow, green;
  wire [2:0] counter;

  // Instancia del DUT (Device Under Test)
  stoplight dut (
    .clk(clk),
    .rst(rst),
    .red(red),
    .yellow(yellow),
    .green(green),
    .counter(counter)
  );

  always begin
    clk = 1; #5;
    clk = 0; #5;
  end

  initial begin
    // Generación del archivo de ondas
    $dumpfile("stoplight.vcd");
    $dumpvars(0, tb_stoplight);

    rst = 1; #12;
    rst = 0; #100
    rst = 1; #18;
    rst = 0; #100
    #1000




    // Estímulos: probar las 4 combinaciones posibles


    // Fin de simulación
    $finish;
  end   

endmodule

stoplight.vcd
$date
	Wed Sep  9 14:52:49 2026
$end
$version
	Icarus Verilog
$end
$timescale
	1ns
$end
$scope module tb_stoplight $end
$var wire 1 ! yellow $end
$var wire 1 " red $end
$var wire 1 # green $end
$var wire 3 $ counter [2:0] $end
$var reg 1 % clk $end
$var reg 1 & rst $end
$scope module dut $end
$var wire 1 % clk $end
$var wire 1 & rst $end
$var wire 1 ! yellow $end
$var wire 1 " red $end
$var wire 1 # green $end
$var parameter 2 ' S0 $end
$var parameter 2 ( S1 $end
$var parameter 2 ) S2 $end
$var parameter 2 * S3 $end
$var reg 3 + counter [2:0] $end
$var reg 3 , next_counter [2:0] $end
$var reg 2 - next_state [1:0] $end
$var reg 2 . state [1:0] $end
$upscope $end
$upscope $end
$enddefinitions $end
$comment Show the parameter values. $end
$dumpall
b11 *
b10 )
b1 (
b0 '
$end
#0
$dumpvars
b0 .
b0 -
b1 ,
b0 +
1&
1%
b0 $
1#
0"
0!
$end
#5
0%
#10
1%
#12
0&
#15
0%
#20
b10 ,
b1 $
b1 +
1%
#25
0%
#30
b11 ,
b10 $
b10 +
1%
#35
0%
#40
b100 ,
b11 $
b11 +
1%
#45
0%
#50
b1 -
b0 ,
b100 $
b100 +
1%
#55
0%
#60
b1 ,
1!
b0 $
b0 +
0#
b1 .
1%
#65
0%
#70
b10 -
b0 ,
b1 $
b1 +
1%
#75
0%
#80
b1 ,
0!
b0 $
b0 +
1"
b10 .
1%
#85
0%
#90
b10 ,
b1 $
b1 +
1%
#95
0%
#100
b11 ,
b10 $
b10 +
1%
#105
0%
#110
b11 -
b0 ,
b11 $
b11 +
1%
#112
b1 ,
b0 -
b0 $
b0 +
0"
1#
b0 .
1&
#115
0%
#120
1%
#125
0%
#130
b10 ,
b1 $
b1 +
1%
0&
#135
0%
#140
b11 ,
b10 $
b10 +
1%
#145
0%
#150
b100 ,
b11 $
b11 +
1%
#155
0%
#160
b1 -
b0 ,
b100 $
b100 +
1%
#165
0%
#170
b1 ,
1!
b0 $
b0 +
0#
b1 .
1%
#175
0%
#180
b10 -
b0 ,
b1 $
b1 +
1%
#185
0%
#190
b1 ,
0!
b0 $
b0 +
1"
b10 .
1%
#195
0%
#200
b10 ,
b1 $
b1 +
1%
#205
0%
#210
b11 ,
b10 $
b10 +
1%
#215
0%
#220
b11 -
b0 ,
b11 $
b11 +
1%
#225
0%
#230
b1 ,
1!
b0 $
b0 +
0"
b11 .
1%
#235
0%
#240
b0 -
b0 ,
b1 $
b1 +
1%
#245
0%
#250
b1 ,
0!
b0 $
b0 +
1#
b0 .
1%
#255
0%
#260
b10 ,
b1 $
b1 +
1%
#265
0%
#270
b11 ,
b10 $
b10 +
1%
#275
0%
#280
b100 ,
b11 $
b11 +
1%
#285
0%
#290
b1 -
b0 ,
b100 $
b100 +
1%
#295
0%
#300
b1 ,
1!
b0 $
b0 +
0#
b1 .
1%
#305
0%
#310
b10 -
b0 ,
b1 $
b1 +
1%
#315
0%
#320
b1 ,
0!
b0 $
b0 +
1"
b10 .
1%
#325
0%
#330
b10 ,
b1 $
b1 +
1%
#335
0%
#340
b11 ,
b10 $
b10 +
1%
#345
0%
#350
b11 -
b0 ,
b11 $
b11 +
1%
#355
0%
#360
b1 ,
1!
b0 $
b0 +
0"
b11 .
1%
#365
0%
#370
b0 -
b0 ,
b1 $
b1 +
1%
#375
0%
#380
b1 ,
0!
b0 $
b0 +
1#
b0 .
1%
#385
0%
#390
b10 ,
b1 $
b1 +
1%
#395
0%
#400
b11 ,
b10 $
b10 +
1%
#405
0%
#410
b100 ,
b11 $
b11 +
1%
#415
0%
#420
b1 -
b0 ,
b100 $
b100 +
1%
#425
0%
#430
b1 ,
1!
b0 $
b0 +
0#
b1 .
1%
#435
0%
#440
b10 -
b0 ,
b1 $
b1 +
1%
#445
0%
#450
b1 ,
0!
b0 $
b0 +
1"
b10 .
1%
#455
0%
#460
b10 ,
b1 $
b1 +
1%
#465
0%
#470
b11 ,
b10 $
b10 +
1%
#475
0%
#480
b11 -
b0 ,
b11 $
b11 +
1%
#485
0%
#490
b1 ,
1!
b0 $
b0 +
0"
b11 .
1%
#495
0%
#500
b0 -
b0 ,
b1 $
b1 +
1%
#505
0%
#510
b1 ,
0!
b0 $
b0 +
1#
b0 .
1%
#515
0%
#520
b10 ,
b1 $
b1 +
1%
#525
0%
#530
b11 ,
b10 $
b10 +
1%
#535
0%
#540
b100 ,
b11 $
b11 +
1%
#545
0%
#550
b1 -
b0 ,
b100 $
b100 +
1%
#555
0%
#560
b1 ,
1!
b0 $
b0 +
0#
b1 .
1%
#565
0%
#570
b10 -
b0 ,
b1 $
b1 +
1%
#575
0%
#580
b1 ,
0!
b0 $
b0 +
1"
b10 .
1%
#585
0%
#590
b10 ,
b1 $
b1 +
1%
#595
0%
#600
b11 ,
b10 $
b10 +
1%
#605
0%
#610
b11 -
b0 ,
b11 $
b11 +
1%
#615
0%
#620
b1 ,
1!
b0 $
b0 +
0"
b11 .
1%
#625
0%
#630
b0 -
b0 ,
b1 $
b1 +
1%
#635
0%
#640
b1 ,
0!
b0 $
b0 +
1#
b0 .
1%
#645
0%
#650
b10 ,
b1 $
b1 +
1%
#655
0%
#660
b11 ,
b10 $
b10 +
1%
#665
0%
#670
b100 ,
b11 $
b11 +
1%
#675
0%
#680
b1 -
b0 ,
b100 $
b100 +
1%
#685
0%
#690
b1 ,
1!
b0 $
b0 +
0#
b1 .
1%
#695
0%
#700
b10 -
b0 ,
b1 $
b1 +
1%
#705
0%
#710
b1 ,
0!
b0 $
b0 +
1"
b10 .
1%
#715
0%
#720
b10 ,
b1 $
b1 +
1%
#725
0%
#730
b11 ,
b10 $
b10 +
1%
#735
0%
#740
b11 -
b0 ,
b11 $
b11 +
1%
#745
0%
#750
b1 ,
1!
b0 $
b0 +
0"
b11 .
1%
#755
0%
#760
b0 -
b0 ,
b1 $
b1 +
1%
#765
0%
#770
b1 ,
0!
b0 $
b0 +
1#
b0 .
1%
#775
0%
#780
b10 ,
b1 $
b1 +
1%
#785
0%
#790
b11 ,
b10 $
b10 +
1%
#795
0%
#800
b100 ,
b11 $
b11 +
1%
#805
0%
#810
b1 -
b0 ,
b100 $
b100 +
1%
#815
0%
#820
b1 ,
1!
b0 $
b0 +
0#
b1 .
1%
#825
0%
#830
b10 -
b0 ,
b1 $
b1 +
1%
#835
0%
#840
b1 ,
0!
b0 $
b0 +
1"
b10 .
1%
#845
0%
#850
b10 ,
b1 $
b1 +
1%
#855
0%
#860
b11 ,
b10 $
b10 +
1%
#865
0%
#870
b11 -
b0 ,
b11 $
b11 +
1%
#875
0%
#880
b1 ,
1!
b0 $
b0 +
0"
b11 .
1%
#885
0%
#890
b0 -
b0 ,
b1 $
b1 +
1%
#895
0%
#900
b1 ,
0!
b0 $
b0 +
1#
b0 .
1%
#905
0%
#910
b10 ,
b1 $
b1 +
1%
#915
0%
#920
b11 ,
b10 $
b10 +
1%
#925
0%
#930
b100 ,
b11 $
b11 +
1%
#935
0%
#940
b1 -
b0 ,
b100 $
b100 +
1%
#945
0%
#950
b1 ,
1!
b0 $
b0 +
0#
b1 .
1%
#955
0%
#960
b10 -
b0 ,
b1 $
b1 +
1%
#965
0%
#970
b1 ,
0!
b0 $
b0 +
1"
b10 .
1%
#975
0%
#980
b10 ,
b1 $
b1 +
1%
#985
0%
#990
b11 ,
b10 $
b10 +
1%
#995
0%
#1000
b11 -
b0 ,
b11 $
b11 +
1%
#1005
0%
#1010
b1 ,
1!
b0 $
b0 +
0"
b11 .
1%
#1015
0%
#1020
b0 -
b0 ,
b1 $
b1 +
1%
#1025
0%
#1030
b1 ,
0!
b0 $
b0 +
1#
b0 .
1%
#1035
0%
#1040
b10 ,
b1 $
b1 +
1%
#1045
0%
#1050
b11 ,
b10 $
b10 +
1%
#1055
0%
#1060
b100 ,
b11 $
b11 +
1%
#1065
0%
#1070
b1 -
b0 ,
b100 $
b100 +
1%
#1075
0%
#1080
b1 ,
1!
b0 $
b0 +
0#
b1 .
1%
#1085
0%
#1090
b10 -
b0 ,
b1 $
b1 +
1%
#1095
0%
#1100
b1 ,
0!
b0 $
b0 +
1"
b10 .
1%
#1105
0%
#1110
b10 ,
b1 $
b1 +
1%
#1115
0%
#1120
b11 ,
b10 $
b10 +
1%
#1125
0%
#1130
b11 -
b0 ,
b11 $
b11 +
1%
#1135
0%
#1140
b1 ,
1!
b0 $
b0 +
0"
b11 .
1%
#1145
0%
#1150
b0 -
b0 ,
b1 $
b1 +
1%
#1155
0%
#1160
b1 ,
0!
b0 $
b0 +
1#
b0 .
1%
#1165
0%
#1170
b10 ,
b1 $
b1 +
1%
#1175
0%
#1180
b11 ,
b10 $
b10 +
1%
#1185
0%
#1190
b100 ,
b11 $
b11 +
1%
#1195
0%
#1200
b1 -
b0 ,
b100 $
b100 +
1%
#1205
0%
#1210
b1 ,
1!
b0 $
b0 +
0#
b1 .
1%
#1215
0%
#1220
b10 -
b0 ,
b1 $
b1 +
1%
#1225
0%
#1230
b1 ,
0!
b0 $
b0 +
1"
b10 .
1%
