Contador.v
module Contador(
    input wire clk,
    input wire reset,
    input wire start,
    input wire cancel,
    input wire [1:0] num_veces,
    input wire [3:0] num_suma,

    output reg [5:0] acc,
    output reg done
);


reg [2:0] counter;

// Declaración de estado actual y estado siguiente
reg [1:0] next_state;
reg [1:0] state; 


// Codificación de los estados de la FMS

parameter [1:0] IDLE = 2'b00;
parameter [1:0] LOAD = 2'b01;
parameter [1:0] ADD = 2'b10;
parameter [1:0] DONE = 2'b11;


// Configuración de reset y cambio de estado en cada ciclo de reloj

always @(posedge clk or posedge reset) begin

    if (reset) begin
        state <= IDLE;
        acc <= 0;
        counter <= 0;
    end else begin

        state <= next_state;

    end else begin

        case (state)
            LOAD: begin
                acc <= 0;
                counter <= 0;
            end
            ADD: begin
                acc <= acc + num_suma;
                counter <= counter + 1;
            end
            DONE: begin
                // Mantener el valor de acc y counter en DONE
            end
            default: begin
                // No hacer nada en otros estados
            end
        endcase
    end 
end

// Bloque combinacional para la lógica de transición de estados y salida de la FMS

always @(*) begin
    
    done = 0;
    
    case (state)

        IDLE: begin
            if (start) begin
                next_state = LOAD;
            end else begin
                next_state = IDLE;
            end
        end

        LOAD: begin
            next_state = ADD;
        end

        ADD: begin

            if (cancel) begin
                next_state = LOAD;

            end else begin
                if (num_veces == 2'b00) begin
                    if (acc + num_suma >= 20) begin
                        next_state = DONE;
                    end else begin
                        next_state = ADD;
                    end
                end else begin
                    if (counter == num_veces + 1)begin
                        next_state = DONE;
                    end else begin
                        next_state = ADD;
                    end
                end
            end
        end

        DONE: begin
            done = 1;
            next_state = IDLE;
            end

        default: begin
            next_state = IDLE;
        end
    endcase
end


endmodule

tb_Contador.v
`timescale 1ns/1ps

module tb_Contador;

    // Entradas del módulo
    reg clk;
    reg reset;
    reg start;
    reg cancel;
    reg [1:0] num_veces;
    reg [3:0] num_suma;

    // Salidas del módulo
    wire [5:0] acc;
    wire done;


    // Instancia del módulo
    Contador uut (
        .clk(clk),
        .reset(reset),
        .start(start),
        .cancel(cancel),
        .num_veces(num_veces),
        .num_suma(num_suma),
        .acc(acc),
        .done(done)
    );


    // Generación del reloj
    always begin
        #5 clk = ~clk;
    end


    // Estímulos de prueba
    initial begin

        // Valores iniciales
        clk = 0;
        reset = 1;
        start = 0;
        cancel = 0;
        num_veces = 0;
        num_suma = 0;

        // Generar archivo para GTKWave
        $dumpfile("tb_Contador.vcd");
        $dumpvars(0, tb_Contador);


        // ============================
        // RESET
        // ============================

        #10;
        reset = 0;


        // ============================
        // PRUEBA 1:
        // num_veces = 1
        // Debe sumar 3 veces
        // x = 5
        // Resultado esperado: 15
        // ============================

        num_veces = 2'b01;
        num_suma = 4'd5;

        #10;
        start = 1;

        #10;
        start = 0;

        // Esperar a que termine
        #100;


        // ============================
        // PRUEBA 2:
        // num_veces = 2
        // Debe sumar 4 veces
        // x = 5
        // Resultado esperado: 20
        // ============================

        num_veces = 2'b10;
        num_suma = 4'd5;

        #10;
        start = 1;

        #10;
        start = 0;

        #100;


        // ============================
        // PRUEBA 3:
        // CANCELACIÓN
        //
        // num_veces = 3
        // Debería sumar 5 veces
        // x = 4
        //
        // Pero se cancela
        //
        // Esperado:
        // 0 → 4 → 8 → 12
        //       ↓
        //     CANCEL
        //       ↓
        //      LOAD
        //       ↓
        //      acc = 0
        // ============================

        num_veces = 2'b11;
        num_suma = 4'd4;

        #10;
        start = 1;

        #10;
        start = 0;

        // Dejar que haga algunas sumas
        #30;

        // Activar cancelación
        cancel = 1;

        #10;
        cancel = 0;

        // Esperar para observar el resultado
        #100;


        // ============================
        // PRUEBA 4:
        // num_veces = 0
        // Sumar hasta acc >= 20
        // x = 6
        //
        // Esperado:
        // 0 → 6 → 12 → 18 → 24
        // ============================

        num_veces = 2'b00;
        num_suma = 4'd6;

        #10;
        start = 1;

        #10;
        start = 0;

        #150;


        // Terminar simulación
        $finish;

    end

endmodule

tb_Contador.vcd
$date
	Wed Sep 16 18:58:02 2026
$end
$version
	Icarus Verilog
$end
$timescale
	1ps
$end
$scope module tb_Contador $end
$var wire 1 ! done $end
$var wire 6 " acc [5:0] $end
$var reg 1 # cancel $end
$var reg 1 $ clk $end
$var reg 4 % num_suma [3:0] $end
$var reg 2 & num_veces [1:0] $end
$var reg 1 ' reset $end
$var reg 1 ( start $end
$scope module uut $end
$var wire 1 # cancel $end
$var wire 1 $ clk $end
$var wire 4 ) num_suma [3:0] $end
$var wire 2 * num_veces [1:0] $end
$var wire 1 ' reset $end
$var wire 1 ( start $end
$var parameter 2 + ADD $end
$var parameter 2 , DONE $end
$var parameter 2 - IDLE $end
$var parameter 2 . LOAD $end
$var reg 6 / acc [5:0] $end
$var reg 3 0 counter [2:0] $end
$var reg 1 ! done $end
$var reg 2 1 next_state [1:0] $end
$var reg 2 2 state [1:0] $end
$upscope $end
$upscope $end
$enddefinitions $end
$comment Show the parameter values. $end
$dumpall
b1 .
b0 -
b11 ,
b10 +
$end
#0
$dumpvars
b0 2
b0 1
b0 0
b0 /
b0 *
b0 )
0(
1'
b0 &
b0 %
0$
0#
b0 "
0!
$end
#5000
1$
#10000
0$
b101 %
b101 )
b1 &
b1 *
0'
#15000
1$
#20000
b1 1
0$
1(
#25000
b10 1
b1 2
1$
#30000
0$
0(
#35000
b10 2
1$
#40000
0$
#45000
b1 0
b101 "
b101 /
1$
#50000
0$
#55000
b11 1
b10 0
b1010 "
b1010 /
1$
#60000
0$
#65000
b0 1
1!
b11 0
b1111 "
b1111 /
b11 2
1$
#70000
0$
#75000
0!
b0 2
1$
#80000
0$
#85000
1$
#90000
0$
#95000
1$
#100000
0$
#105000
1$
#110000
0$
#115000
1$
#120000
0$
#125000
1$
#130000
0$
b10 &
b10 *
#135000
1$
#140000
b1 1
0$
1(
#145000
b10 1
b1 2
1$
#150000
0$
0(
#155000
b10 2
b0 0
b0 "
b0 /
1$
#160000
0$
#165000
b1 0
b101 "
b101 /
1$
#170000
0$
#175000
b10 0
b1010 "
b1010 /
1$
#180000
0$
#185000
b11 1
b11 0
b1111 "
b1111 /
1$
#190000
0$
#195000
b0 1
1!
b11 2
b100 0
b10100 "
b10100 /
1$
#200000
0$
#205000
0!
b0 2
1$
#210000
0$
#215000
1$
#220000
0$
#225000
1$
#230000
0$
#235000
1$
#240000
0$
#245000
1$
#250000
0$
b100 %
b100 )
b11 &
b11 *
#255000
1$
#260000
b1 1
0$
1(
#265000
b10 1
b1 2
1$
#270000
0$
0(
#275000
b10 2
b0 0
b0 "
b0 /
1$
#280000
0$
#285000
b1 0
b100 "
b100 /
1$
#290000
0$
#295000
b10 0
b1000 "
b1000 /
1$
#300000
b1 1
0$
1#
#305000
b10 1
b11 0
b1100 "
b1100 /
b1 2
1$
#310000
0$
0#
#315000
b10 2
b0 0
b0 "
b0 /
1$
#320000
0$
#325000
b1 0
b100 "
b100 /
1$
#330000
0$
#335000
b10 0
b1000 "
b1000 /
1$
#340000
0$
#345000
b11 0
b1100 "
b1100 /
1$
#350000
0$
#355000
b11 1
b100 0
b10000 "
b10000 /
1$
#360000
0$
#365000
b0 1
1!
b101 0
b10100 "
b10100 /
b11 2
1$
#370000
0$
#375000
0!
b0 2
1$
#380000
0$
#385000
1$
#390000
0$
#395000
1$
#400000
0$
#405000
1$
#410000
0$
b110 %
b110 )
b0 &
b0 *
#415000
1$
#420000
b1 1
0$
1(
#425000
b10 1
b1 2
1$
#430000
0$
0(
#435000
b10 2
b0 0
b0 "
b0 /
1$
#440000
0$
#445000
b1 0
b110 "
b110 /
1$
#450000
0$
#455000
b10 0
b1100 "
b1100 /
1$
#460000
0$
#465000
b11 1
b11 0
b10010 "
b10010 /
1$
#470000
0$
#475000
b0 1
1!
b11 2
b100 0
b11000 "
b11000 /
1$
#480000
0$
#485000
0!
b0 2
1$
