Contador.v
module Contador (
    input wire clk,
    input wire reset,
    input wire start,
    input wire cancel,
    input wire [1:0] num_veces,
    input wire [3:0] num_suma,

    output reg [5:0] acc,
    output reg done
);

    // =========================================================
    // 1. DATAPATH (Ruta de Datos)
    // =========================================================
    reg [2:0] counter;
    
    // Señales de Control (FSM -> Datapath)
    wire clr_acc_cnt;
    wire en_acc_cnt;

    // Señales de Estatus de 1 bit (Datapath -> FSM)
    wire mode_zero  = (num_veces == 2'b00);
    wire comp_ge_20 = (acc + num_suma >= 6'd20);
    wire count_done = (counter == num_veces + 3'd1);

    // Registros del Datapath
    always @(posedge clk or posedge reset) begin
        if (reset) begin
            acc     <= 6'd0;
            counter <= 3'd0;
        end else if (clr_acc_cnt) begin
            acc     <= 6'd0;
            counter <= 3'd0;
        end else if (en_acc_cnt) begin
            acc     <= acc + num_suma;
            counter <= counter + 3'd1;
        end
    end

    // =========================================================
    // 2. CONTROLADOR (FSM Pura)
    // =========================================================
    parameter IDLE = 2'b00, LOAD = 2'b01, ADD = 2'b10, DONE = 2'b11;
    reg [1:0] state, next_state;

    // Actualización de estado
    always @(posedge clk or posedge reset) begin
        if (reset) state <= IDLE;
        else       state <= next_state;
    end

    // Lógica combinacional de control y estado siguiente
    reg clr_acc_cnt_reg, en_acc_cnt_reg;
    assign clr_acc_cnt = clr_acc_cnt_reg;
    assign en_acc_cnt  = en_acc_cnt_reg;

    always @(*) begin
        next_state      = state;
        clr_acc_cnt_reg = 1'b0;
        en_acc_cnt_reg  = 1'b0;
        done            = 1'b0;

        case (state)
            IDLE: begin
                if (start) next_state = LOAD;
            end

            LOAD: begin
                clr_acc_cnt_reg = 1'b1;
                next_state      = ADD;
            end

            ADD: begin
                en_acc_cnt_reg = 1'b1;
                if (cancel) begin
                    next_state = LOAD;
                end else if ((mode_zero && comp_ge_20) || (!mode_zero && count_done)) begin
                    next_state = DONE;
                end else begin
                    next_state = ADD;
                end
            end

            DONE: begin
                done       = 1'b1;
                next_state = IDLE;
            end

            default: next_state = IDLE;
        endcase
    end

endmodule

tb_Contador.v
`timescale 1ns/1ps

module tb_Contador;

    // Entradas del módulo
    reg clk;
    reg reset;
    reg start;
    reg cancel;
    reg [1:0] num_veces;
    reg [3:0] num_suma;

    // Salidas del módulo
    wire [5:0] acc;
    wire done;

    // Instancia del módulo
    Contador uut (
        .clk(clk),
        .reset(reset),
        .start(start),
        .cancel(cancel),
        .num_veces(num_veces),
        .num_suma(num_suma),
        .acc(acc),
        .done(done)
    );

    // Generación del reloj
    always begin
        #5 clk = ~clk;
    end

    // Estímulos de prueba
    initial begin

        // Valores iniciales
        clk = 0;
        reset = 1;
        start = 0;
        cancel = 0;
        num_veces = 0;
        num_suma = 0;

        // Generar archivo para GTKWave
        $dumpfile("tb_Contador.vcd");
        $dumpvars(0, tb_Contador);

        // ============================
        // RESET
        // ============================

        #10;
        reset = 0;


        // ============================
        // PRUEBA 1:
        // num_veces = 1
        // Debe sumar 3 veces
        // x = 5
        // Resultado esperado: 15
        // ============================

        num_veces = 2'b01;
        num_suma = 4'd5;

        #10;
        start = 1;

        #10;
        start = 0;

        // Esperar a que termine
        #100;


        // ============================
        // PRUEBA 2:
        // num_veces = 2
        // Debe sumar 4 veces
        // x = 5
        // Resultado esperado: 20
        // ============================

        num_veces = 2'b10;
        num_suma = 4'd5;

        #10;
        start = 1;

        #10;
        start = 0;

        #100;


        // ============================
        // PRUEBA 3:
        // CANCELACIÓN
        //
        // num_veces = 3
        // Debería sumar 5 veces
        // x = 4
        //
        // Pero se cancela
        //
        // Esperado:
        // 0 → 4 → 8 → 12
        //           ↓
        //         CANCEL
        //           ↓
        //         LOAD
        //           ↓
        //        acc = 0
        // ============================

        num_veces = 2'b11;
        num_suma = 4'd4;

        #10;
        start = 1;

        #10;
        start = 0;

        // Dejar que haga algunas sumas
        #30;

        // Activar cancelación
        cancel = 1;

        #10;
        cancel = 0;

        // Esperar para observar el resultado
        #100;


        // ============================
        // PRUEBA 4:
        // num_veces = 0
        // Sumar hasta acc >= 20
        // x = 6
        //
        // Esperado:
        // 0 → 6 → 12 → 18 → 24
        // ============================

        num_veces = 2'b00;
        num_suma = 4'd6;

        #10;
        start = 1;

        #10;
        start = 0;

        #150;


        // Terminar simulación
        $finish;

    end

endmodule

tb_Contador.vcd
$date
	Wed Sep 16 23:37:41 2026
$end
$version
	Icarus Verilog
$end
$timescale
	1ps
$end
$scope module tb_Contador $end
$var wire 1 ! done $end
$var wire 6 " acc [5:0] $end
$var reg 1 # cancel $end
$var reg 1 $ clk $end
$var reg 4 % num_suma [3:0] $end
$var reg 2 & num_veces [1:0] $end
$var reg 1 ' reset $end
$var reg 1 ( start $end
$scope module uut $end
$var wire 1 # cancel $end
$var wire 1 $ clk $end
$var wire 1 ) clr_acc_cnt $end
$var wire 1 * en_acc_cnt $end
$var wire 4 + num_suma [3:0] $end
$var wire 2 , num_veces [1:0] $end
$var wire 1 ' reset $end
$var wire 1 ( start $end
$var wire 1 - mode_zero $end
$var wire 1 . count_done $end
$var wire 1 / comp_ge_20 $end
$var parameter 2 0 ADD $end
$var parameter 2 1 DONE $end
$var parameter 2 2 IDLE $end
$var parameter 2 3 LOAD $end
$var reg 6 4 acc [5:0] $end
$var reg 1 5 clr_acc_cnt_reg $end
$var reg 3 6 counter [2:0] $end
$var reg 1 ! done $end
$var reg 1 7 en_acc_cnt_reg $end
$var reg 2 8 next_state [1:0] $end
$var reg 2 9 state [1:0] $end
$upscope $end
$upscope $end
$enddefinitions $end
$comment Show the parameter values. $end
$dumpall
b1 3
b0 2
b11 1
b10 0
$end
#0
$dumpvars
b0 9
b0 8
07
b0 6
05
b0 4
0/
0.
1-
b0 ,
b0 +
0*
0)
0(
1'
b0 &
b0 %
0$
0#
b0 "
0!
$end
#5000
1$
#10000
0$
b101 %
b101 +
0-
b1 &
b1 ,
0'
#15000
1$
#20000
b1 8
0$
1(
#25000
b10 8
1)
15
b1 9
1$
#30000
1)
15
b10 8
0$
0(
#35000
1*
17
0)
05
b10 9
1$
#40000
0$
#45000
b1 6
b101 "
b101 4
1$
#50000
0$
#55000
b11 8
1*
17
1.
b10 6
b1010 "
b1010 4
1$
#60000
0$
#65000
b0 8
1!
0*
07
b11 9
0.
b11 6
1/
b1111 "
b1111 4
1$
#70000
0$
#75000
0!
b0 9
1$
#80000
0$
#85000
1$
#90000
0$
#95000
1$
#100000
0$
#105000
1$
#110000
0$
#115000
1$
#120000
0$
#125000
1$
#130000
0$
1.
b10 &
b10 ,
#135000
1$
#140000
b1 8
0$
1(
#145000
b10 8
1)
15
b1 9
1$
#150000
1)
15
b10 8
0$
0(
#155000
1*
17
0)
05
0.
b0 6
0/
b0 "
b0 4
b10 9
1$
#160000
0$
#165000
b1 6
b101 "
b101 4
1$
#170000
0$
#175000
b10 6
b1010 "
b1010 4
1$
#180000
0$
#185000
b11 8
1*
17
1.
b11 6
1/
b1111 "
b1111 4
1$
#190000
0$
#195000
b0 8
1!
0*
07
0.
b100 6
b10100 "
b10100 4
b11 9
1$
#200000
0$
#205000
0!
b0 9
1$
#210000
0$
#215000
1$
#220000
0$
#225000
1$
#230000
0$
#235000
1$
#240000
0$
#245000
1$
#250000
0$
b100 %
b100 +
1.
b11 &
b11 ,
#255000
1$
#260000
b1 8
0$
1(
#265000
b10 8
1)
15
b1 9
1$
#270000
1)
15
b10 8
0$
0(
#275000
1*
17
0)
05
0.
b0 6
0/
b0 "
b0 4
b10 9
1$
#280000
0$
#285000
b1 6
b100 "
b100 4
1$
#290000
0$
#295000
b10 6
b1000 "
b1000 4
1$
#300000
b1 8
1*
17
0$
1#
#305000
b10 8
1)
15
0*
07
b1 9
b11 6
b1100 "
b1100 4
1$
#310000
1)
15
b10 8
0$
0#
#315000
1*
17
0)
05
b0 6
b0 "
b0 4
b10 9
1$
#320000
0$
#325000
b1 6
b100 "
b100 4
1$
#330000
0$
#335000
b10 6
b1000 "
b1000 4
1$
#340000
0$
#345000
b11 6
b1100 "
b1100 4
1$
#350000
0$
#355000
b11 8
1*
17
1.
b100 6
1/
b10000 "
b10000 4
1$
#360000
0$
#365000
b0 8
1!
0*
07
b11 9
0.
b101 6
b10100 "
b10100 4
1$
#370000
0$
#375000
0!
b0 9
1$
#380000
0$
#385000
1$
#390000
0$
#395000
1$
#400000
0$
#405000
1$
#410000
0$
b110 %
b110 +
1-
b0 &
b0 ,
#415000
1$
#420000
b1 8
0$
1(
#425000
b10 8
1)
15
b1 9
1$
#430000
1)
15
b10 8
0$
0(
#435000
1*
17
0)
05
b0 6
0/
b0 "
b0 4
b10 9
1$
#440000
0$
#445000
1*
17
1.
b1 6
b110 "
b110 4
1$
#450000
0$
#455000
1*
17
0.
b10 6
b1100 "
b1100 4
1$
#460000
0$
#465000
b11 8
1*
17
b11 6
1/
b10010 "
b10010 4
1$
#470000
0$
#475000
b0 8
1!
0*
07
b100 6
b11000 "
b11000 4
b11 9
1$
#480000
0$
#485000
0!
b0 9
1$
