src/accumulator.v
`timescale 1ns/1ps

// Los modos 00 y 11 acumulan hasta alcanzar o superar 20; 01 y 10
// realizan tres y cuatro sumas. Las entradas se consultan durante la operacion,
// por lo que deben mantenerse estables si no se quiere cambiar su criterio.
module accumulator(
    input wire clk,
    input wire reset,
    input wire start,
    input wire cancel,
    input wire [1:0] num_veces,
    input wire [3:0] num_suma,
    output reg [5:0] acc,
    output reg done
);

// counter cuenta las sumas realizadas; acc conserva el resultado acumulado.
// Cinco bits permiten contar las veinte sumas necesarias cuando num_suma = 1.
reg [4:0] counter;
reg [1:0] next_state;
reg [1:0] state;

parameter [1:0] IDLE = 2'b00;
parameter [1:0] LOAD = 2'b01;
parameter [1:0] ADD = 2'b10;
parameter [1:0] DONE = 2'b11;

// Registro de estado con reset asincrono. El datapath se reinicia en otro bloque.
always @(posedge clk or posedge reset) begin
    if (reset) begin
        state <= IDLE;
    end
    else begin
        state <= next_state;
    end
end

// Logica combinacional de transicion y salida done.
// start solo se atiende en IDLE; done se activa unicamente en DONE.
always @(*) begin
    done = 0;

    case (state)
        IDLE: begin
            if (start) begin
                next_state = LOAD;
            end
            else begin
                next_state = IDLE;
            end
        end

        LOAD: begin
            // Se mantiene el datapath en cero hasta recibir un sumando valido.
            if (num_suma == 0) next_state = LOAD;
            else next_state = ADD;
        end

        ADD: begin
            // La cancelacion tiene prioridad incluso si esta suma iba a ser la ultima.
            if (cancel) begin
                next_state = LOAD;
            end
            else if (num_suma == 0) begin
                // Si el sumando pasa a cero durante la operacion, se reinicia
                // la carga y se espera un nuevo valor, sin generar done.
                next_state = LOAD;
            end
            else begin
                if (num_veces == 2'b00 || num_veces == 2'b11) begin
                    // Se anticipa el resultado: la ultima suma se registra en el
                    // mismo flanco que lleva a DONE. Comparar solo acc sumaria de mas.
                    if (acc + num_suma >= 20) begin
                        next_state = DONE;
                    end
                    else begin
                        next_state = ADD;
                    end
                end
                else begin
                    // Falta la suma del proximo flanco para completar num_veces + 2.
                    if (counter == num_veces + 1) begin
                        next_state = DONE;
                    end
                    else begin
                        next_state = ADD;
                    end
                end
            end
        end

        // Se permanece un ciclo en DONE y luego se espera una nueva solicitud.
        DONE: begin
            done = 1;
            next_state = IDLE;
        end

        default: begin
            next_state = IDLE;
        end
    endcase
end

// Datapath: las asignaciones no bloqueantes usan el estado anterior al flanco.
// Por eso ADD tambien suma al pasar a DONE o LOAD. Si hubo cancelacion,
// el borrado se realiza un flanco despues, cuando el estado previo ya es LOAD.
always @(posedge clk or posedge reset) begin
    if (reset) begin
        acc <= 0;
        counter <= 0;
    end
    else begin
        case (state)
            LOAD: begin
                acc <= 0;
                counter <= 0;
            end
            ADD: begin
                acc <= acc + num_suma;
                counter <= counter + 1;
            end
            DONE: begin
                // Mantener el valor de acc y counter en DONE.
            end
            default: begin
                // Sin asignacion, los registros conservan su valor mientras se espera.
            end
        endcase
    end
end

endmodule

src/tb_accumulator.v
`timescale 1ns/1ps

// Verifica resultados parciales y finales, los cuatro modos y la cancelacion.
// Los estimulos y las lecturas se realizan en flancos negativos, separados
// del flanco positivo en el que el circuito actualiza sus registros.
module tb_accumulator;
  reg clk, reset, start, cancel;
  reg [1:0] num_veces;
  reg [3:0] num_suma;
  wire [5:0] acc;
  wire done;
  // Permite relacionar cada intervalo de GTKWave con una prueba concreta.
  integer test_id;
  integer mode_index, sum_index;

  accumulator uut (
    .clk(clk), .reset(reset), .start(start), .cancel(cancel),
    .num_veces(num_veces), .num_suma(num_suma), .acc(acc), .done(done)
  );

  // Periodo de reloj de 10 ns.
  initial clk = 0;
  always #5 clk = ~clk;

  // Solo se acepta un 1 conocido; una condicion falsa o indeterminada es un error.
  task check;
    input condition;
    input [8*120-1:0] message;
    begin
      if (condition !== 1'b1)
        $fatal(1, "FAIL accumulator test=%0d t=%0t: %0s", test_id, $time, message);
    end
  endtask

  // Aplica start durante un ciclo y espera a que LOAD limpie los registros.
  // Al terminar esta tarea, el circuito esta en ADD y aun no ha realizado sumas.
  task begin_operation;
    input integer id;
    input [1:0] mode;
    input [3:0] value;
    begin
      @(negedge clk);
      check(uut.state === 2'd0 && done === 1'b0, "se esperaba IDLE");
      test_id = id;
      num_veces = mode;
      num_suma = value;
      start = 1;
      @(negedge clk);
      check(uut.state === 2'd1, "start no produjo LOAD");
      start = 0;
      @(negedge clk);
      check(uut.state === 2'd2 && acc === 6'd0 && uut.counter === 3'd0,
            "LOAD no limpio el datapath");
    end
  endtask

  // Comprueba una suma. last_sum indica si debe coincidir con la entrada a DONE.
  task sum_cycle;
    input [5:0] expected_acc;
    input [4:0] expected_count;
    input last_sum;
    begin
      @(negedge clk);
      check(acc === expected_acc, "suma parcial incorrecta");
      check(uut.counter === expected_count, "numero de sumas incorrecto");
      check(done === last_sum, "done anticipado o ausente");
      if (last_sum) check(uut.state === 2'd3, "se esperaba DONE");
      else check(uut.state === 2'd2, "se esperaba ADD");
    end
  endtask

  // Verifica el resultado, que done dure un ciclo y que acc se conserve en reposo.
  task finish_operation;
    input [5:0] expected_acc;
    begin
      check(done === 1'b1 && acc === expected_acc, "resultado final incorrecto");
      $display("OK accumulator test=%0d acc=%0d, t=%0t", test_id, acc, $time);
      @(negedge clk);
      check(done === 1'b0 && uut.state === 2'd0, "done no duro un ciclo");
      check(acc === expected_acc, "resultado no se conserva en IDLE");
      repeat (2) @(negedge clk);
    end
  endtask

  // Se solicita cancelacion desde ADD. Todavia ocurre la suma de ese flanco;
  // last_acc es ese valor intermedio, antes de que LOAD borre los registros.
  task cancel_operation;
    input [5:0] last_acc;
    begin
      cancel = 1;
      @(negedge clk);
      check(uut.state === 2'd1 && done === 1'b0, "cancel debe tener prioridad");
      check(acc === last_acc, "suma al entrar en LOAD incorrecta");
      cancel = 0;
      @(negedge clk);
      check(uut.state === 2'd2 && acc === 6'd0 && uut.counter === 3'd0,
            "cancel no reinicio el datapath");
    end
  endtask

  initial begin
    // Incluye señales internas, como state y counter, para revisar la FSM.
    $dumpfile("accumulator.vcd");
    $dumpvars(0, tb_accumulator);
    test_id = 0;
    reset = 1; start = 0; cancel = 0;
    num_veces = 0; num_suma = 0;
    repeat (2) @(negedge clk);
    check(uut.state === 2'd0 && acc === 6'd0 && uut.counter === 3'd0 && done === 1'b0,
          "reset incorrecto");
    reset = 0;

    // Modo 01: tres sumas de 5, con resultado 15.
    begin_operation(1, 2'b01, 4'd5);
    sum_cycle(5, 1, 0); sum_cycle(10, 2, 0); sum_cycle(15, 3, 1);
    finish_operation(15);

    // Modo 10: cuatro sumas de 5, con resultado 20.
    begin_operation(2, 2'b10, 4'd5);
    sum_cycle(5, 1, 0); sum_cycle(10, 2, 0);
    sum_cycle(15, 3, 0); sum_cycle(20, 4, 1);
    finish_operation(20);

    // Modo 11: umbral de 20 con cancelacion. Con sumando 4 requiere cinco sumas.
    begin_operation(3, 2'b11, 4'd4);
    sum_cycle(4, 1, 0); sum_cycle(8, 2, 0);
    cancel_operation(12);
    sum_cycle(4, 1, 0); sum_cycle(8, 2, 0); sum_cycle(12, 3, 0);
    sum_cycle(16, 4, 0); sum_cycle(20, 5, 1);
    finish_operation(20);

    // Modo 00: 18 todavia es menor que 20; la ultima suma lleva el resultado a 24.
    begin_operation(4, 2'b00, 4'd6);
    sum_cycle(6, 1, 0); sum_cycle(12, 2, 0);
    sum_cycle(18, 3, 0); sum_cycle(24, 4, 1);
    finish_operation(24);

    // Igualdad exacta al umbral: debe terminar en 20, no en 25.
    begin_operation(5, 2'b00, 4'd5);
    sum_cycle(5, 1, 0); sum_cycle(10, 2, 0);
    sum_cycle(15, 3, 0); sum_cycle(20, 4, 1);
    finish_operation(20);

    // cancel y condicion de fin coinciden: debe ir a LOAD, no a DONE.
    begin_operation(6, 2'b01, 4'd5);
    sum_cycle(5, 1, 0); sum_cycle(10, 2, 0);
    cancel_operation(15);
    sum_cycle(5, 1, 0); sum_cycle(10, 2, 0); sum_cycle(15, 3, 1);
    finish_operation(15);

    // El modo 11 ya no significa cinco sumas: con 6 termina en cuatro, como 00.
    begin_operation(7, 2'b11, 4'd6);
    sum_cycle(6, 1, 0); sum_cycle(12, 2, 0);
    sum_cycle(18, 3, 0); sum_cycle(24, 4, 1);
    finish_operation(24);

    // Los modos de cantidad fija admiten el mayor sumando sin desbordar acc.
    begin_operation(8, 2'b01, 4'd15);
    sum_cycle(15, 1, 0); sum_cycle(30, 2, 0); sum_cycle(45, 3, 1);
    finish_operation(45);
    begin_operation(9, 2'b10, 4'd15);
    sum_cycle(15, 1, 0); sum_cycle(30, 2, 0);
    sum_cycle(45, 3, 0); sum_cycle(60, 4, 1);
    finish_operation(60);

    // Pruebas 10 a 13: todos los modos esperan en LOAD con sumando cero.
    // Al cambiarlo a 5, la operacion comienza sin otro pulso start.
    for (mode_index = 0; mode_index < 4; mode_index = mode_index + 1) begin
      @(negedge clk);
      test_id = 10 + mode_index;
      num_veces = mode_index; num_suma = 0; start = 1;
      @(negedge clk);
      check(uut.state === 2'd1, "se esperaba LOAD con sumando cero");
      start = 0;
      repeat (4) begin
        @(negedge clk);
        check(uut.state === 2'd1 && acc === 6'd0 && uut.counter === 5'd0 && done === 1'b0,
              "LOAD debe esperar con registros limpios y done desactivado");
      end
      num_suma = 5;
      @(negedge clk);
      check(uut.state === 2'd2 && acc === 6'd0, "no salio de LOAD al recibir sumando");
      sum_cycle(5, 1, 0); sum_cycle(10, 2, 0);
      if (mode_index == 1) begin
        sum_cycle(15, 3, 1); finish_operation(15);
      end
      else begin
        sum_cycle(15, 3, 0); sum_cycle(20, 4, 1); finish_operation(20);
      end
    end

    // Un cero durante ADD devuelve la operacion a LOAD; despues se reinicia.
    begin_operation(14, 2'b00, 4'd6);
    sum_cycle(6, 1, 0);
    num_suma = 0;
    @(negedge clk);
    check(uut.state === 2'd1 && done === 1'b0, "sumando cero no retorno a LOAD");
    repeat (3) begin
      @(negedge clk);
      check(uut.state === 2'd1 && acc === 6'd0 && uut.counter === 5'd0 && done === 1'b0,
            "espera en LOAD incorrecta tras interrumpir ADD");
    end
    num_suma = 6;
    @(negedge clk);
    check(uut.state === 2'd2 && acc === 6'd0, "no reinicio tras sumando cero");
    sum_cycle(6, 1, 0); sum_cycle(12, 2, 0);
    sum_cycle(18, 3, 0); sum_cycle(24, 4, 1); finish_operation(24);

    // Caso mas largo por umbral: veinte sumas de 1, sin desbordar el contador.
    begin_operation(15, 2'b11, 4'd1);
    for (sum_index = 1; sum_index <= 20; sum_index = sum_index + 1)
      sum_cycle(sum_index, sum_index, sum_index == 20);
    finish_operation(20);

    $display("PASS accumulator: quince pruebas, modos, espera en LOAD, cancel y done");
    $finish;
  end

  initial begin
    // Un bloqueo o una operacion que no termina debe hacer fallar la prueba.
    #10000;
    $fatal(1, "Timeout accumulator");
  end
endmodule

src/accumulator.vcd
$date
	Sun Sep 20 13:30:35 2026
$end
$version
	Icarus Verilog
$end
$timescale
	1ps
$end
$scope module tb_accumulator $end
$var wire 1 ! done $end
$var wire 6 " acc [5:0] $end
$var reg 1 # cancel $end
$var reg 1 $ clk $end
$var reg 4 % num_suma [3:0] $end
$var reg 2 & num_veces [1:0] $end
$var reg 1 ' reset $end
$var reg 1 ( start $end
$var integer 32 ) mode_index [31:0] $end
$var integer 32 * sum_index [31:0] $end
$var integer 32 + test_id [31:0] $end
$scope module uut $end
$var wire 1 # cancel $end
$var wire 1 $ clk $end
$var wire 4 , num_suma [3:0] $end
$var wire 2 - num_veces [1:0] $end
$var wire 1 ' reset $end
$var wire 1 ( start $end
$var parameter 2 . ADD $end
$var parameter 2 / DONE $end
$var parameter 2 0 IDLE $end
$var parameter 2 1 LOAD $end
$var reg 6 2 acc [5:0] $end
$var reg 5 3 counter [4:0] $end
$var reg 1 ! done $end
$var reg 2 4 next_state [1:0] $end
$var reg 2 5 state [1:0] $end
$upscope $end
$scope task begin_operation $end
$var reg 2 6 mode [1:0] $end
$var reg 4 7 value [3:0] $end
$var integer 32 8 id [31:0] $end
$upscope $end
$scope task cancel_operation $end
$var reg 6 9 last_acc [5:0] $end
$upscope $end
$scope task check $end
$var reg 1 : condition $end
$var reg 960 ; message [959:0] $end
$upscope $end
$scope task finish_operation $end
$var reg 6 < expected_acc [5:0] $end
$upscope $end
$scope task sum_cycle $end
$var reg 6 = expected_acc [5:0] $end
$var reg 5 > expected_count [4:0] $end
$var reg 1 ? last_sum $end
$upscope $end
$upscope $end
$enddefinitions $end
$comment Show the parameter values. $end
$dumpall
b1 1
b0 0
b11 /
b10 .
$end
#0
$dumpvars
x?
bx >
bx =
bx <
bx ;
x:
bx 9
bx 8
bx 7
bx 6
b0 5
b0 4
b0 3
b0 2
b0 -
b0 ,
b0 +
bx *
bx )
0(
1'
b0 &
b0 %
0$
0#
b0 "
0!
$end
#5000
1$
#10000
0$
#15000
1$
#20000
b101 7
b1 6
b1 8
0'
b1110010011001010111001101100101011101000010000001101001011011100110001101101111011100100111001001100101011000110111010001101111 ;
1:
0$
#25000
1$
#30000
b1 4
1(
b101 %
b101 ,
b1 &
b1 -
b1 +
b1110011011001010010000001100101011100110111000001100101011100100110000101100010011000010010000001001001010001000100110001000101 ;
0$
#35000
b10 4
b1 5
1$
#40000
0(
b11100110111010001100001011100100111010000100000011011100110111100100000011100000111001001101111011001000111010101101010011011110010000001001100010011110100000101000100 ;
0$
#45000
b10 5
1$
#50000
0?
b1 >
b101 =
b100110001001111010000010100010000100000011011100110111100100000011011000110100101101101011100000110100101101111001000000110010101101100001000000110010001100001011101000110000101110000011000010111010001101000 ;
0$
#55000
b1 3
b101 "
b101 2
1$
#60000
b10 >
b1010 =
b11100110110010100100000011001010111001101110000011001010111001001100001011000100110000100100000010000010100010001000100 ;
0$
#65000
b11 4
b10 3
b1010 "
b1010 2
1$
#70000
1?
b11 >
b1111 =
b11100110110010100100000011001010111001101110000011001010111001001100001011000100110000100100000010000010100010001000100 ;
0$
#75000
b0 4
1!
b11 5
b11 3
b1111 "
b1111 2
1$
#80000
b1111 <
b111001001100101011100110111010101101100011101000110000101100100011011110010000001100110011010010110111001100001011011000010000001101001011011100110001101101111011100100111001001100101011000110111010001101111 ;
0$
#85000
0!
b0 5
1$
#90000
b111001001100101011100110111010101101100011101000110000101100100011011110010000001101110011011110010000001110011011001010010000001100011011011110110111001110011011001010111001001110110011000010010000001100101011011100010000001001001010001000100110001000101 ;
0$
#95000
1$
#100000
0$
#105000
1$
#110000
b10 6
b10 8
0$
#115000
1$
#120000
b1 4
1(
b10 &
b10 -
b10 +
b1110011011001010010000001100101011100110111000001100101011100100110000101100010011000010010000001001001010001000100110001000101 ;
0$
#125000
b10 4
b1 5
1$
#130000
0(
b11100110111010001100001011100100111010000100000011011100110111100100000011100000111001001101111011001000111010101101010011011110010000001001100010011110100000101000100 ;
0$
#135000
b10 5
b0 3
b0 "
b0 2
1$
#140000
0?
b1 >
b101 =
b100110001001111010000010100010000100000011011100110111100100000011011000110100101101101011100000110100101101111001000000110010101101100001000000110010001100001011101000110000101110000011000010111010001101000 ;
0$
#145000
b1 3
b101 "
b101 2
1$
#150000
b10 >
b1010 =
b11100110110010100100000011001010111001101110000011001010111001001100001011000100110000100100000010000010100010001000100 ;
0$
#155000
b10 3
b1010 "
b1010 2
1$
#160000
b11 >
b1111 =
b11100110110010100100000011001010111001101110000011001010111001001100001011000100110000100100000010000010100010001000100 ;
0$
#165000
b11 4
b11 3
b1111 "
b1111 2
1$
#170000
1?
b100 >
b10100 =
b11100110110010100100000011001010111001101110000011001010111001001100001011000100110000100100000010000010100010001000100 ;
0$
#175000
b0 4
1!
b11 5
b100 3
b10100 "
b10100 2
1$
#180000
b10100 <
b111001001100101011100110111010101101100011101000110000101100100011011110010000001100110011010010110111001100001011011000010000001101001011011100110001101101111011100100111001001100101011000110111010001101111 ;
0$
#185000
0!
b0 5
1$
#190000
b111001001100101011100110111010101101100011101000110000101100100011011110010000001101110011011110010000001110011011001010010000001100011011011110110111001110011011001010111001001110110011000010010000001100101011011100010000001001001010001000100110001000101 ;
0$
#195000
1$
#200000
0$
#205000
1$
#210000
b100 7
b11 6
b11 8
0$
#215000
1$
#220000
b1 4
1(
b100 %
b100 ,
b11 &
b11 -
b11 +
b1110011011001010010000001100101011100110111000001100101011100100110000101100010011000010010000001001001010001000100110001000101 ;
0$
#225000
b10 4
b1 5
1$
#230000
0(
b11100110111010001100001011100100111010000100000011011100110111100100000011100000111001001101111011001000111010101101010011011110010000001001100010011110100000101000100 ;
0$
#235000
b10 5
b0 3
b0 "
b0 2
1$
#240000
0?
b1 >
b100 =
b100110001001111010000010100010000100000011011100110111100100000011011000110100101101101011100000110100101101111001000000110010101101100001000000110010001100001011101000110000101110000011000010111010001101000 ;
0$
#245000
b1 3
b100 "
b100 2
1$
#250000
b10 >
b1000 =
b11100110110010100100000011001010111001101110000011001010111001001100001011000100110000100100000010000010100010001000100 ;
0$
#255000
b10 3
b1000 "
b1000 2
1$
#260000
b1 4
1#
b1100 9
b11100110110010100100000011001010111001101110000011001010111001001100001011000100110000100100000010000010100010001000100 ;
0$
#265000
b10 4
b11 3
b1100 "
b1100 2
b1 5
1$
#270000
0#
b11100110111010101101101011000010010000001100001011011000010000001100101011011100111010001110010011000010111001000100000011001010110111000100000010011000100111101000001010001000010000001101001011011100110001101101111011100100111001001100101011000110111010001100001 ;
0$
#275000
b10 5
b0 3
b0 "
b0 2
1$
#280000
b1 >
b100 =
b11000110110000101101110011000110110010101101100001000000110111001101111001000000111001001100101011010010110111001101001011000110110100101101111001000000110010101101100001000000110010001100001011101000110000101110000011000010111010001101000 ;
0$
#285000
b1 3
b100 "
b100 2
1$
#290000
b10 >
b1000 =
b11100110110010100100000011001010111001101110000011001010111001001100001011000100110000100100000010000010100010001000100 ;
0$
#295000
b10 3
b1000 "
b1000 2
1$
#300000
b11 >
b1100 =
b11100110110010100100000011001010111001101110000011001010111001001100001011000100110000100100000010000010100010001000100 ;
0$
#305000
b11 3
b1100 "
b1100 2
1$
#310000
b100 >
b10000 =
b11100110110010100100000011001010111001101110000011001010111001001100001011000100110000100100000010000010100010001000100 ;
0$
#315000
b11 4
b100 3
b10000 "
b10000 2
1$
#320000
1?
b101 >
b10100 =
b11100110110010100100000011001010111001101110000011001010111001001100001011000100110000100100000010000010100010001000100 ;
0$
#325000
b0 4
1!
b101 3
b10100 "
b10100 2
b11 5
1$
#330000
b111001001100101011100110111010101101100011101000110000101100100011011110010000001100110011010010110111001100001011011000010000001101001011011100110001101101111011100100111001001100101011000110111010001101111 ;
0$
#335000
0!
b0 5
1$
#340000
b111001001100101011100110111010101101100011101000110000101100100011011110010000001101110011011110010000001110011011001010010000001100011011011110110111001110011011001010111001001110110011000010010000001100101011011100010000001001001010001000100110001000101 ;
0$
#345000
1$
#350000
0$
#355000
1$
#360000
b110 7
b0 6
b100 8
0$
#365000
1$
#370000
b1 4
1(
b110 %
b110 ,
b0 &
b0 -
b100 +
b1110011011001010010000001100101011100110111000001100101011100100110000101100010011000010010000001001001010001000100110001000101 ;
0$
#375000
b10 4
b1 5
1$
#380000
0(
b11100110111010001100001011100100111010000100000011011100110111100100000011100000111001001101111011001000111010101101010011011110010000001001100010011110100000101000100 ;
0$
#385000
b0 3
b0 "
b0 2
b10 5
1$
#390000
0?
b1 >
b110 =
b100110001001111010000010100010000100000011011100110111100100000011011000110100101101101011100000110100101101111001000000110010101101100001000000110010001100001011101000110000101110000011000010111010001101000 ;
0$
#395000
b1 3
b110 "
b110 2
1$
#400000
b10 >
b1100 =
b11100110110010100100000011001010111001101110000011001010111001001100001011000100110000100100000010000010100010001000100 ;
0$
#405000
b10 3
b1100 "
b1100 2
1$
#410000
b11 >
b10010 =
b11100110110010100100000011001010111001101110000011001010111001001100001011000100110000100100000010000010100010001000100 ;
0$
#415000
b11 4
b11 3
b10010 "
b10010 2
1$
#420000
1?
b100 >
b11000 =
b11100110110010100100000011001010111001101110000011001010111001001100001011000100110000100100000010000010100010001000100 ;
0$
#425000
b0 4
1!
b100 3
b11000 "
b11000 2
b11 5
1$
#430000
b11000 <
b111001001100101011100110111010101101100011101000110000101100100011011110010000001100110011010010110111001100001011011000010000001101001011011100110001101101111011100100111001001100101011000110111010001101111 ;
0$
#435000
0!
b0 5
1$
#440000
b111001001100101011100110111010101101100011101000110000101100100011011110010000001101110011011110010000001110011011001010010000001100011011011110110111001110011011001010111001001110110011000010010000001100101011011100010000001001001010001000100110001000101 ;
0$
#445000
1$
#450000
0$
#455000
1$
#460000
b101 7
b101 8
0$
#465000
1$
#470000
b1 4
1(
b101 %
b101 ,
b101 +
b1110011011001010010000001100101011100110111000001100101011100100110000101100010011000010010000001001001010001000100110001000101 ;
0$
#475000
b10 4
b1 5
1$
#480000
0(
b11100110111010001100001011100100111010000100000011011100110111100100000011100000111001001101111011001000111010101101010011011110010000001001100010011110100000101000100 ;
0$
#485000
b0 3
b0 "
b0 2
b10 5
1$
#490000
0?
b1 >
b101 =
b100110001001111010000010100010000100000011011100110111100100000011011000110100101101101011100000110100101101111001000000110010101101100001000000110010001100001011101000110000101110000011000010111010001101000 ;
0$
#495000
b1 3
b101 "
b101 2
1$
#500000
b10 >
b1010 =
b11100110110010100100000011001010111001101110000011001010111001001100001011000100110000100100000010000010100010001000100 ;
0$
#505000
b10 3
b1010 "
b1010 2
1$
#510000
b11 >
b1111 =
b11100110110010100100000011001010111001101110000011001010111001001100001011000100110000100100000010000010100010001000100 ;
0$
#515000
b11 4
b11 3
b1111 "
b1111 2
1$
#520000
1?
b100 >
b10100 =
b11100110110010100100000011001010111001101110000011001010111001001100001011000100110000100100000010000010100010001000100 ;
0$
#525000
b0 4
1!
b100 3
b10100 "
b10100 2
b11 5
1$
#530000
b10100 <
b111001001100101011100110111010101101100011101000110000101100100011011110010000001100110011010010110111001100001011011000010000001101001011011100110001101101111011100100111001001100101011000110111010001101111 ;
0$
#535000
0!
b0 5
1$
#540000
b111001001100101011100110111010101101100011101000110000101100100011011110010000001101110011011110010000001110011011001010010000001100011011011110110111001110011011001010111001001110110011000010010000001100101011011100010000001001001010001000100110001000101 ;
0$
#545000
1$
#550000
0$
#555000
1$
#560000
b1 6
b110 8
0$
#565000
1$
#570000
b1 4
1(
b1 &
b1 -
b110 +
b1110011011001010010000001100101011100110111000001100101011100100110000101100010011000010010000001001001010001000100110001000101 ;
0$
#575000
b10 4
b1 5
1$
#580000
0(
b11100110111010001100001011100100111010000100000011011100110111100100000011100000111001001101111011001000111010101101010011011110010000001001100010011110100000101000100 ;
0$
#585000
b0 3
b0 "
b0 2
b10 5
1$
#590000
0?
b1 >
b101 =
b100110001001111010000010100010000100000011011100110111100100000011011000110100101101101011100000110100101101111001000000110010101101100001000000110010001100001011101000110000101110000011000010111010001101000 ;
0$
#595000
b1 3
b101 "
b101 2
1$
#600000
b10 >
b1010 =
b11100110110010100100000011001010111001101110000011001010111001001100001011000100110000100100000010000010100010001000100 ;
0$
#605000
b11 4
b10 3
b1010 "
b1010 2
1$
#610000
b1 4
1#
b1111 9
b11100110110010100100000011001010111001101110000011001010111001001100001011000100110000100100000010000010100010001000100 ;
0$
#615000
b10 4
b1 5
b11 3
b1111 "
b1111 2
1$
#620000
0#
b11100110111010101101101011000010010000001100001011011000010000001100101011011100111010001110010011000010111001000100000011001010110111000100000010011000100111101000001010001000010000001101001011011100110001101101111011100100111001001100101011000110111010001100001 ;
0$
#625000
b0 3
b0 "
b0 2
b10 5
1$
#630000
b1 >
b101 =
b11000110110000101101110011000110110010101101100001000000110111001101111001000000111001001100101011010010110111001101001011000110110100101101111001000000110010101101100001000000110010001100001011101000110000101110000011000010111010001101000 ;
0$
#635000
b1 3
b101 "
b101 2
1$
#640000
b10 >
b1010 =
b11100110110010100100000011001010111001101110000011001010111001001100001011000100110000100100000010000010100010001000100 ;
0$
#645000
b11 4
b10 3
b1010 "
b1010 2
1$
#650000
1?
b11 >
b1111 =
b11100110110010100100000011001010111001101110000011001010111001001100001011000100110000100100000010000010100010001000100 ;
0$
#655000
b0 4
1!
b11 5
b11 3
b1111 "
b1111 2
1$
#660000
b1111 <
b111001001100101011100110111010101101100011101000110000101100100011011110010000001100110011010010110111001100001011011000010000001101001011011100110001101101111011100100111001001100101011000110111010001101111 ;
0$
#665000
0!
b0 5
1$
#670000
b111001001100101011100110111010101101100011101000110000101100100011011110010000001101110011011110010000001110011011001010010000001100011011011110110111001110011011001010111001001110110011000010010000001100101011011100010000001001001010001000100110001000101 ;
0$
#675000
1$
#680000
0$
#685000
1$
#690000
b110 7
b11 6
b111 8
0$
#695000
1$
#700000
b1 4
1(
b110 %
b110 ,
b11 &
b11 -
b111 +
b1110011011001010010000001100101011100110111000001100101011100100110000101100010011000010010000001001001010001000100110001000101 ;
0$
#705000
b10 4
b1 5
1$
#710000
0(
b11100110111010001100001011100100111010000100000011011100110111100100000011100000111001001101111011001000111010101101010011011110010000001001100010011110100000101000100 ;
0$
#715000
b10 5
b0 3
b0 "
b0 2
1$
#720000
0?
b1 >
b110 =
b100110001001111010000010100010000100000011011100110111100100000011011000110100101101101011100000110100101101111001000000110010101101100001000000110010001100001011101000110000101110000011000010111010001101000 ;
0$
#725000
b1 3
b110 "
b110 2
1$
#730000
b10 >
b1100 =
b11100110110010100100000011001010111001101110000011001010111001001100001011000100110000100100000010000010100010001000100 ;
0$
#735000
b10 3
b1100 "
b1100 2
1$
#740000
b11 >
b10010 =
b11100110110010100100000011001010111001101110000011001010111001001100001011000100110000100100000010000010100010001000100 ;
0$
#745000
b11 4
b11 3
b10010 "
b10010 2
1$
#750000
1?
b100 >
b11000 =
b11100110110010100100000011001010111001101110000011001010111001001100001011000100110000100100000010000010100010001000100 ;
0$
#755000
b0 4
1!
b11 5
b100 3
b11000 "
b11000 2
1$
#760000
b11000 <
b111001001100101011100110111010101101100011101000110000101100100011011110010000001100110011010010110111001100001011011000010000001101001011011100110001101101111011100100111001001100101011000110111010001101111 ;
0$
#765000
0!
b0 5
1$
#770000
b111001001100101011100110111010101101100011101000110000101100100011011110010000001101110011011110010000001110011011001010010000001100011011011110110111001110011011001010111001001110110011000010010000001100101011011100010000001001001010001000100110001000101 ;
0$
#775000
1$
#780000
0$
#785000
1$
#790000
b1111 7
b1 6
b1000 8
0$
#795000
1$
#800000
b1 4
1(
b1111 %
b1111 ,
b1 &
b1 -
b1000 +
b1110011011001010010000001100101011100110111000001100101011100100110000101100010011000010010000001001001010001000100110001000101 ;
0$
#805000
b10 4
b1 5
1$
#810000
0(
b11100110111010001100001011100100111010000100000011011100110111100100000011100000111001001101111011001000111010101101010011011110010000001001100010011110100000101000100 ;
0$
#815000
b10 5
b0 3
b0 "
b0 2
1$
#820000
0?
b1 >
b1111 =
b100110001001111010000010100010000100000011011100110111100100000011011000110100101101101011100000110100101101111001000000110010101101100001000000110010001100001011101000110000101110000011000010111010001101000 ;
0$
#825000
b1 3
b1111 "
b1111 2
1$
#830000
b10 >
b11110 =
b11100110110010100100000011001010111001101110000011001010111001001100001011000100110000100100000010000010100010001000100 ;
0$
#835000
b11 4
b10 3
b11110 "
b11110 2
1$
#840000
1?
b11 >
b101101 =
b11100110110010100100000011001010111001101110000011001010111001001100001011000100110000100100000010000010100010001000100 ;
0$
#845000
b0 4
1!
b11 3
b101101 "
b101101 2
b11 5
1$
#850000
b101101 <
b111001001100101011100110111010101101100011101000110000101100100011011110010000001100110011010010110111001100001011011000010000001101001011011100110001101101111011100100111001001100101011000110111010001101111 ;
0$
#855000
0!
b0 5
1$
#860000
b111001001100101011100110111010101101100011101000110000101100100011011110010000001101110011011110010000001110011011001010010000001100011011011110110111001110011011001010111001001110110011000010010000001100101011011100010000001001001010001000100110001000101 ;
0$
#865000
1$
#870000
0$
#875000
1$
#880000
b10 6
b1001 8
0$
#885000
1$
#890000
b1 4
1(
b10 &
b10 -
b1001 +
b1110011011001010010000001100101011100110111000001100101011100100110000101100010011000010010000001001001010001000100110001000101 ;
0$
#895000
b10 4
b1 5
1$
#900000
0(
b11100110111010001100001011100100111010000100000011011100110111100100000011100000111001001101111011001000111010101101010011011110010000001001100010011110100000101000100 ;
0$
#905000
b0 3
b0 "
b0 2
b10 5
1$
#910000
0?
b1 >
b1111 =
b100110001001111010000010100010000100000011011100110111100100000011011000110100101101101011100000110100101101111001000000110010101101100001000000110010001100001011101000110000101110000011000010111010001101000 ;
0$
#915000
b1 3
b1111 "
b1111 2
1$
#920000
b10 >
b11110 =
b11100110110010100100000011001010111001101110000011001010111001001100001011000100110000100100000010000010100010001000100 ;
0$
#925000
b10 3
b11110 "
b11110 2
1$
#930000
b11 >
b101101 =
b11100110110010100100000011001010111001101110000011001010111001001100001011000100110000100100000010000010100010001000100 ;
0$
#935000
b11 4
b11 3
b101101 "
b101101 2
1$
#940000
1?
b100 >
b111100 =
b11100110110010100100000011001010111001101110000011001010111001001100001011000100110000100100000010000010100010001000100 ;
0$
#945000
b0 4
1!
b100 3
b111100 "
b111100 2
b11 5
1$
#950000
b111100 <
b111001001100101011100110111010101101100011101000110000101100100011011110010000001100110011010010110111001100001011011000010000001101001011011100110001101101111011100100111001001100101011000110111010001101111 ;
0$
#955000
0!
b0 5
1$
#960000
b111001001100101011100110111010101101100011101000110000101100100011011110010000001101110011011110010000001110011011001010010000001100011011011110110111001110011011001010111001001110110011000010010000001100101011011100010000001001001010001000100110001000101 ;
0$
#965000
1$
#970000
0$
#975000
1$
#980000
b0 )
0$
#985000
1$
#990000
b1 4
1(
b0 %
b0 ,
b0 &
b0 -
b1010 +
0$
#995000
b1 5
1$
#1000000
0(
b11100110110010100100000011001010111001101110000011001010111001001100001011000100110000100100000010011000100111101000001010001000010000001100011011011110110111000100000011100110111010101101101011000010110111001100100011011110010000001100011011001010111001001101111 ;
0$
