src/control_bytetx.v
`timescale 1ns/1ns

// Envia ocho bits, empezando por el menos significativo (LSB).
// Es un envio de datos sin bits de inicio o parada de un protocolo UART.
module control_bytetx(
    input clk,
    input rst,
    input [7:0] data_in,
    input start,
    output reg done,
    output reg busy,
    output reg tx
);

// Cada bit dura esta cantidad de ciclos. El contador de 3 bits permite de 1 a 8.
parameter CLKS_PER_BIT = 4;

// Los registros next_* preparan los valores que se guardaran en el proximo flanco.
// bit_count identifica el bit enviado; tick_cnt mide su tiempo de permanencia.
reg next_busy;
reg [1:0] state, next_state;
reg [7:0] shift_reg, next_shift_reg;
reg [3:0] bit_count, next_bit_count;
reg [2:0] tick_cnt, next_tick_cnt;

parameter S_IDLE = 2'b00;
parameter S_LOAD = 2'b01;
parameter S_BIT_HOLD = 2'b10;
parameter S_DONE = 2'b11;

// Unico bloque que escribe los registros, incluido busy. El reset asincrono
// aborta cualquier envio, limpia los contadores y devuelve el estado a reposo.
always @(posedge clk or posedge rst) begin
    if (rst) begin
        state <= S_IDLE;
        busy <= 1'b0;
        bit_count <= 4'd0;
        tick_cnt <= 3'd0;
        shift_reg <= 8'd0;
    end
    else begin
        state <= next_state;
        bit_count <= next_bit_count;
        tick_cnt <= next_tick_cnt;
        shift_reg <= next_shift_reg;
        busy <= next_busy;
    end
end

// Valores por defecto: linea en reposo alto, done desactivado y datos conservados.
// Cada estado modifica solo los valores necesarios para su operacion.
always @(*) begin
    next_state = state;
    done = 1'b0;
    // busy tiene un unico controlador secuencial; aqui se calcula su proximo valor.
    next_busy = 1'b0;
    tx = 1'b1;
    next_bit_count = bit_count;
    next_tick_cnt = tick_cnt;
    next_shift_reg = shift_reg;

    case (state)
        // Al aceptar start, busy se activara junto con la entrada a S_LOAD.
        S_IDLE: begin
            done = 1'b0;
            if (start) begin
                next_state = S_LOAD;
                next_busy = 1'b1;
            end
            else begin
                tx = 1'b1;
                next_state = S_IDLE;
            end
        end

        // El byte se captura al salir de S_LOAD; data_in debe ser valido hasta entonces.
        S_LOAD: begin
            next_busy = 1'b1;
            next_bit_count = 4'd0;
            next_tick_cnt = 3'd0;
            next_shift_reg = data_in;
            next_state = S_BIT_HOLD;
        end

        // Se mantiene el mismo bit hasta completar CLKS_PER_BIT ciclos.
        S_BIT_HOLD: begin
            next_busy = 1'b1;
            tx = shift_reg[0];
            if (tick_cnt != CLKS_PER_BIT - 1) begin
                next_tick_cnt = tick_cnt + 3'd1;
                next_state = S_BIT_HOLD;
            end
            // El bit 7 es el ultimo. busy bajara al entrar en S_DONE,
            // justo cuando done indique que el byte ya se termino de enviar.
            else if (bit_count == 7) begin
                next_state = S_DONE;
                next_busy = 1'b0;
            end
            else begin
                next_bit_count = bit_count + 4'd1;
                // El siguiente bit pasa a la posicion cero, que alimenta tx.
                next_shift_reg = {1'b0, shift_reg[7:1]};
                next_tick_cnt = 3'd0;
                next_state = S_BIT_HOLD;
            end
        end

        // Pulso de finalizacion de un ciclo; tx vuelve al nivel de reposo.
        S_DONE: begin
            done = 1'b1;
            next_state = S_IDLE;
            next_busy = 1'b0;
        end

        default: begin
            next_state = S_IDLE;
        end
    endcase
end

endmodule

src/tb_bytetx.v
`timescale 1ns/1ns
`include "control_bytetx.v"
`timescale 1ns/1ns

// Comprueba el envio LSB-first, la duracion de cada bit y las señales de control.
// Tambien interrumpe un envio con reset y comprueba una transmision posterior.
module tb_bytetx;
  parameter CLKS_PER_BIT = 4;
  reg clk, rst, start;
  // recibido reconstruye el byte para compararlo con el dato original.
  reg [7:0] data_in, recibido;
  wire done, busy, tx;
  // Identifica cada envio en las formas de onda y en los mensajes de error.
  integer test_id;

  control_bytetx #(.CLKS_PER_BIT(CLKS_PER_BIT)) dut (
    .clk(clk), .rst(rst), .data_in(data_in), .start(start),
    .done(done), .busy(busy), .tx(tx)
  );

  // Reloj de periodo 10 ns: con CLKS_PER_BIT = 4, cada bit dura 40 ns.
  initial clk = 0;
  always #5 clk = ~clk;

  // Se detiene ante una condicion falsa o indeterminada, indicando el instante.
  task check;
    input condition;
    input [8*120-1:0] message;
    begin
      if (condition !== 1'b1)
        $fatal(1, "FAIL bytetx test=%0d t=%0t: %0s", test_id, $time, message);
    end
  endtask

  // Genera start por un ciclo y espera la carga del byte. Se usa el flanco
  // negativo para que los registros del flanco positivo ya esten actualizados.
  task begin_transmission;
    input integer id;
    input [7:0] value;
    begin
      @(negedge clk);
      check(dut.state === 2'd0 && busy === 1'b0 && done === 1'b0 && tx === 1'b1,
            "reposo incorrecto");
      test_id = id;
      data_in = value;
      start = 1;
      recibido = 0;
      @(negedge clk);
      check(dut.state === 2'd1 && busy === 1'b1 && done === 1'b0 && tx === 1'b1,
            "LOAD o busy incorrectos");
      start = 0;
      @(negedge clk);
      check(dut.state === 2'd2 && dut.shift_reg === value, "carga de byte incorrecta");
      $display("Inicio bytetx test=%0d dato=%h, t=%0t", id, value, $time);
    end
  endtask

  // Recorre los ocho bits y sus ciclos de permanencia, no solo los cambios de tx.
  task send_and_check;
    input integer id;
    input [7:0] value;
    integer bit_index, tick;
    begin
      begin_transmission(id, value);
      // Comprobar cada ciclo de cada bit, incluso entre bits del mismo valor.
      for (bit_index = 0; bit_index < 8; bit_index = bit_index + 1) begin
        for (tick = 0; tick < CLKS_PER_BIT; tick = tick + 1) begin
          check(dut.state === 2'd2 && busy === 1'b1 && done === 1'b0,
                "estado, busy o done durante el envio incorrectos");
          check(tx === value[bit_index], "bit serial incorrecto");
          check(dut.bit_count == bit_index, "indice del bit incorrecto");
          check(dut.tick_cnt == tick, "duracion del bit incorrecta");
          check(dut.shift_reg === (value >> bit_index), "desplazamiento incorrecto");
          // Una muestra por bit basta para reconstruirlo; las demas comprueban
          // que la salida se mantiene estable durante todo el intervalo.
          if (tick == 0) recibido[bit_index] = tx;
          @(negedge clk);
        end
      end
      // Al terminar, done debe subir y busy bajar en el mismo ciclo.
      check(recibido === value, "byte reconstruido incorrecto");
      check(dut.state === 2'd3 && done === 1'b1 && busy === 1'b0 && tx === 1'b1,
            "DONE debe activar done y desactivar busy");
      $display("OK bytetx test=%0d enviado=%h recibido=%h busy=0 done=1, t=%0t",
               id, value, recibido, $time);
      @(negedge clk);
      check(dut.state === 2'd0 && done === 1'b0 && busy === 1'b0 && tx === 1'b1,
            "done no duro un ciclo o busy no volvio a reposo");
      repeat (2) @(negedge clk);
    end
  endtask

  initial begin
    // Guarda tambien los contadores y el registro de desplazamiento internos.
    $dumpfile("bytetx.vcd");
    $dumpvars(0, tb_bytetx);
    test_id = 0;
    rst = 1; start = 0; data_in = 0; recibido = 0;
    repeat (2) @(negedge clk);
    check(busy === 1'b0 && done === 1'b0 && tx === 1'b1 && dut.state === 2'd0,
          "reset inicial incorrecto");
    rst = 0;

    // Estos patrones comprueban cambios de nivel y grupos de bits iguales.
    send_and_check(1, 8'hA5);
    send_and_check(2, 8'hF0);
    send_and_check(3, 8'h01);

    // Reset durante una transmision: busy debe caer sin esperar otro posedge.
    begin_transmission(4, 8'h96);
    repeat (3) @(negedge clk);
    #2 rst = 1;
    #1;
    check(busy === 1'b0 && done === 1'b0 && tx === 1'b1 && dut.state === 2'd0,
          "reset durante envio no limpio las salidas");
    check(dut.shift_reg === 8'd0 && dut.bit_count == 0 && dut.tick_cnt == 0,
          "reset durante envio no limpio el datapath");
    repeat (2) @(negedge clk);
    rst = 0;
    $display("OK bytetx test=4: envio abortado por reset, t=%0t", $time);

    // El circuito debe aceptar un nuevo byte despues de abortar el envio anterior.
    send_and_check(5, 8'h3C);
    $display("PASS bytetx: cuatro bytes completos, temporizacion, busy, done y reset");
    $finish;
  end

  initial begin
    // Limite de seguridad para detectar una simulacion que no termina.
    #20000;
    $fatal(1, "Timeout bytetx");
  end
endmodule

src/bytetx.vcd
$date
	Sun Sep 20 13:31:39 2026
$end
$version
	Icarus Verilog
$end
$timescale
	1ns
$end
$scope module tb_bytetx $end
$var wire 1 ! tx $end
$var wire 1 " done $end
$var wire 1 # busy $end
$var parameter 32 $ CLKS_PER_BIT $end
$var reg 1 % clk $end
$var reg 8 & data_in [7:0] $end
$var reg 8 ' recibido [7:0] $end
$var reg 1 ( rst $end
$var reg 1 ) start $end
$var integer 32 * test_id [31:0] $end
$scope module dut $end
$var wire 1 % clk $end
$var wire 8 + data_in [7:0] $end
$var wire 1 ( rst $end
$var wire 1 ) start $end
$var parameter 32 , CLKS_PER_BIT $end
$var parameter 2 - S_BIT_HOLD $end
$var parameter 2 . S_DONE $end
$var parameter 2 / S_IDLE $end
$var parameter 2 0 S_LOAD $end
$var reg 4 1 bit_count [3:0] $end
$var reg 1 # busy $end
$var reg 1 " done $end
$var reg 4 2 next_bit_count [3:0] $end
$var reg 1 3 next_busy $end
$var reg 8 4 next_shift_reg [7:0] $end
$var reg 2 5 next_state [1:0] $end
$var reg 3 6 next_tick_cnt [2:0] $end
$var reg 8 7 shift_reg [7:0] $end
$var reg 2 8 state [1:0] $end
$var reg 3 9 tick_cnt [2:0] $end
$var reg 1 ! tx $end
$upscope $end
$scope task begin_transmission $end
$var reg 8 : value [7:0] $end
$var integer 32 ; id [31:0] $end
$upscope $end
$scope task check $end
$var reg 1 < condition $end
$var reg 960 = message [959:0] $end
$upscope $end
$scope task send_and_check $end
$var reg 8 > value [7:0] $end
$var integer 32 ? bit_index [31:0] $end
$var integer 32 @ id [31:0] $end
$var integer 32 A tick [31:0] $end
$upscope $end
$upscope $end
$enddefinitions $end
$comment Show the parameter values. $end
$dumpall
b1 0
b0 /
b11 .
b10 -
b100 ,
b100 $
$end
#0
$dumpvars
bx A
bx @
bx ?
bx >
bx =
x<
bx ;
bx :
b0 9
b0 8
b0 7
b0 6
b0 5
b0 4
03
b0 2
b0 1
b0 +
b0 *
0)
1(
b0 '
b0 &
0%
0#
0"
1!
$end
#5
1%
#10
0%
#15
1%
#20
b10100101 :
b1 ;
b10100101 >
b1 @
0(
b11100100110010101110011011001010111010000100000011010010110111001101001011000110110100101100001011011000010000001101001011011100110001101101111011100100111001001100101011000110111010001101111 =
1<
0%
#25
1%
#30
13
b1 5
1)
b10100101 &
b10100101 +
b1 *
b111001001100101011100000110111101110011011011110010000001101001011011100110001101101111011100100111001001100101011000110111010001101111 =
0%
#35
b10 5
b10100101 4
13
1#
b1 8
1%
#40
b10100101 4
13
b10 5
0)
b100110001001111010000010100010000100000011011110010000001100010011101010111001101111001001000000110100101101110011000110110111101110010011100100110010101100011011101000110111101110011 =
0%
#45
b1 6
13
b10100101 7
b10 8
1%
#50
b1 '
b0 A
b0 ?
b1100100011001010111001101110000011011000110000101111010011000010110110101101001011001010110111001110100011011110010000001101001011011100110001101101111011100100111001001100101011000110111010001101111 =
0%
#55
b10 6
13
b1 9
1%
#60
b1100100011001010111001101110000011011000110000101111010011000010110110101101001011001010110111001110100011011110010000001101001011011100110001101101111011100100111001001100101011000110111010001101111 =
b1 A
0%
#65
b11 6
13
b10 9
1%
#70
b1100100011001010111001101110000011011000110000101111010011000010110110101101001011001010110111001110100011011110010000001101001011011100110001101101111011100100111001001100101011000110111010001101111 =
b10 A
0%
#75
b0 6
b1010010 4
b1 2
13
b11 9
1%
#80
b1100100011001010111001101110000011011000110000101111010011000010110110101101001011001010110111001110100011011110010000001101001011011100110001101101111011100100111001001100101011000110111010001101111 =
b11 A
0%
#85
b1 6
0!
13
b1010010 7
b0 9
b1 1
1%
#90
b1100100011001010111001101110000011011000110000101111010011000010110110101101001011001010110111001110100011011110010000001101001011011100110001101101111011100100111001001100101011000110111010001101111 =
b1 ?
b0 A
0%
#95
b10 6
0!
13
b1 9
1%
#100
b1100100011001010111001101110000011011000110000101111010011000010110110101101001011001010110111001110100011011110010000001101001011011100110001101101111011100100111001001100101011000110111010001101111 =
b1 A
0%
#105
b11 6
0!
13
b10 9
1%
#110
b1100100011001010111001101110000011011000110000101111010011000010110110101101001011001010110111001110100011011110010000001101001011011100110001101101111011100100111001001100101011000110111010001101111 =
b10 A
0%
#115
b0 6
b101001 4
b10 2
0!
13
b11 9
1%
#120
b1100100011001010111001101110000011011000110000101111010011000010110110101101001011001010110111001110100011011110010000001101001011011100110001101101111011100100111001001100101011000110111010001101111 =
b11 A
0%
#125
b1 6
1!
13
b101001 7
b0 9
b10 1
1%
#130
b101 '
b1100100011001010111001101110000011011000110000101111010011000010110110101101001011001010110111001110100011011110010000001101001011011100110001101101111011100100111001001100101011000110111010001101111 =
b10 ?
b0 A
0%
#135
b10 6
13
b1 9
1%
#140
b1100100011001010111001101110000011011000110000101111010011000010110110101101001011001010110111001110100011011110010000001101001011011100110001101101111011100100111001001100101011000110111010001101111 =
b1 A
0%
#145
b11 6
13
b10 9
1%
#150
b1100100011001010111001101110000011011000110000101111010011000010110110101101001011001010110111001110100011011110010000001101001011011100110001101101111011100100111001001100101011000110111010001101111 =
b10 A
0%
#155
b0 6
b10100 4
b11 2
13
b11 9
1%
#160
b1100100011001010111001101110000011011000110000101111010011000010110110101101001011001010110111001110100011011110010000001101001011011100110001101101111011100100111001001100101011000110111010001101111 =
b11 A
0%
#165
b1 6
0!
13
b10100 7
b0 9
b11 1
1%
#170
b1100100011001010111001101110000011011000110000101111010011000010110110101101001011001010110111001110100011011110010000001101001011011100110001101101111011100100111001001100101011000110111010001101111 =
b11 ?
b0 A
0%
#175
b10 6
0!
13
b1 9
1%
#180
b1100100011001010111001101110000011011000110000101111010011000010110110101101001011001010110111001110100011011110010000001101001011011100110001101101111011100100111001001100101011000110111010001101111 =
b1 A
0%
#185
b11 6
0!
13
b10 9
1%
#190
b1100100011001010111001101110000011011000110000101111010011000010110110101101001011001010110111001110100011011110010000001101001011011100110001101101111011100100111001001100101011000110111010001101111 =
b10 A
0%
#195
b0 6
b1010 4
b100 2
0!
13
b11 9
1%
#200
b1100100011001010111001101110000011011000110000101111010011000010110110101101001011001010110111001110100011011110010000001101001011011100110001101101111011100100111001001100101011000110111010001101111 =
b11 A
0%
#205
b1 6
0!
13
b1010 7
b0 9
b100 1
1%
#210
b1100100011001010111001101110000011011000110000101111010011000010110110101101001011001010110111001110100011011110010000001101001011011100110001101101111011100100111001001100101011000110111010001101111 =
b100 ?
b0 A
0%
#215
b10 6
0!
13
b1 9
1%
#220
b1100100011001010111001101110000011011000110000101111010011000010110110101101001011001010110111001110100011011110010000001101001011011100110001101101111011100100111001001100101011000110111010001101111 =
b1 A
0%
#225
b11 6
0!
13
b10 9
1%
#230
b1100100011001010111001101110000011011000110000101111010011000010110110101101001011001010110111001110100011011110010000001101001011011100110001101101111011100100111001001100101011000110111010001101111 =
b10 A
0%
#235
b0 6
b101 4
b101 2
0!
13
b11 9
1%
#240
b1100100011001010111001101110000011011000110000101111010011000010110110101101001011001010110111001110100011011110010000001101001011011100110001101101111011100100111001001100101011000110111010001101111 =
b11 A
0%
#245
b1 6
1!
13
b101 7
b0 9
b101 1
1%
#250
b100101 '
b1100100011001010111001101110000011011000110000101111010011000010110110101101001011001010110111001110100011011110010000001101001011011100110001101101111011100100111001001100101011000110111010001101111 =
b101 ?
b0 A
0%
#255
b10 6
13
b1 9
1%
#260
b1100100011001010111001101110000011011000110000101111010011000010110110101101001011001010110111001110100011011110010000001101001011011100110001101101111011100100111001001100101011000110111010001101111 =
b1 A
0%
#265
b11 6
13
b10 9
1%
#270
b1100100011001010111001101110000011011000110000101111010011000010110110101101001011001010110111001110100011011110010000001101001011011100110001101101111011100100111001001100101011000110111010001101111 =
b10 A
0%
#275
b0 6
b10 4
b110 2
13
b11 9
1%
#280
b1100100011001010111001101110000011011000110000101111010011000010110110101101001011001010110111001110100011011110010000001101001011011100110001101101111011100100111001001100101011000110111010001101111 =
b11 A
0%
#285
b1 6
0!
13
b10 7
b0 9
b110 1
1%
#290
b1100100011001010111001101110000011011000110000101111010011000010110110101101001011001010110111001110100011011110010000001101001011011100110001101101111011100100111001001100101011000110111010001101111 =
b110 ?
b0 A
0%
#295
b10 6
0!
13
b1 9
1%
#300
b1100100011001010111001101110000011011000110000101111010011000010110110101101001011001010110111001110100011011110010000001101001011011100110001101101111011100100111001001100101011000110111010001101111 =
b1 A
0%
#305
b11 6
0!
13
b10 9
1%
#310
b1100100011001010111001101110000011011000110000101111010011000010110110101101001011001010110111001110100011011110010000001101001011011100110001101101111011100100111001001100101011000110111010001101111 =
b10 A
0%
#315
b0 6
b1 4
b111 2
0!
13
b11 9
1%
#320
b1100100011001010111001101110000011011000110000101111010011000010110110101101001011001010110111001110100011011110010000001101001011011100110001101101111011100100111001001100101011000110111010001101111 =
b11 A
0%
#325
b1 6
1!
13
b1 7
b0 9
b111 1
1%
#330
b10100101 '
b1100100011001010111001101110000011011000110000101111010011000010110110101101001011001010110111001110100011011110010000001101001011011100110001101101111011100100111001001100101011000110111010001101111 =
b111 ?
b0 A
0%
#335
b10 6
13
b1 9
1%
#340
b1100100011001010111001101110000011011000110000101111010011000010110110101101001011001010110111001110100011011110010000001101001011011100110001101101111011100100111001001100101011000110111010001101111 =
b1 A
0%
#345
b11 6
13
b10 9
1%
#350
b1100100011001010111001101110000011011000110000101111010011000010110110101101001011001010110111001110100011011110010000001101001011011100110001101101111011100100111001001100101011000110111010001101111 =
b10 A
0%
#355
b11 5
03
b11 9
1%
#360
b1100100011001010111001101110000011011000110000101111010011000010110110101101001011001010110111001110100011011110010000001101001011011100110001101101111011100100111001001100101011000110111010001101111 =
b11 A
0%
#365
b0 5
1"
0#
b11 8
1%
#370
b1000100010011110100111001000101001000000110010001100101011000100110010100100000011000010110001101110100011010010111011001100001011100100010000001100100011011110110111001100101001000000111100100100000011001000110010101110011011000010110001101110100011010010111011001100001011100100010000001100010011101010111001101111001 =
b1000 ?
b100 A
0%
#375
0"
b0 8
1%
#380
b110010001101111011011100110010100100000011011100110111100100000011001000111010101110010011011110010000001110101011011100010000001100011011010010110001101101100011011110010000001101111001000000110001001110101011100110111100100100000011011100110111100100000011101100110111101101100011101100110100101101111001000000110000100100000011100100110010101110000011011110111001101101111 =
0%
#385
1%
#390
0%
#395
1%
#400
b11110000 :
b10 ;
b11110000 >
b10 @
0%
#405
1%
#410
13
b1 5
b0 '
1)
b11110000 &
b11110000 +
b10 *
b111001001100101011100000110111101110011011011110010000001101001011011100110001101101111011100100111001001100101011000110111010001101111 =
0%
#415
b10 5
b11110000 4
b0 6
b0 2
13
1#
b1 8
1%
#420
b11110000 4
b0 6
b0 2
13
b10 5
0)
b100110001001111010000010100010000100000011011110010000001100010011101010111001101111001001000000110100101101110011000110110111101110010011100100110010101100011011101000110111101110011 =
0%
#425
b1 6
0!
13
b11110000 7
b0 9
b0 1
b10 8
1%
#430
b0 A
b0 ?
b1100100011001010111001101110000011011000110000101111010011000010110110101101001011001010110111001110100011011110010000001101001011011100110001101101111011100100111001001100101011000110111010001101111 =
0%
#435
b10 6
0!
13
b1 9
1%
#440
b1100100011001010111001101110000011011000110000101111010011000010110110101101001011001010110111001110100011011110010000001101001011011100110001101101111011100100111001001100101011000110111010001101111 =
b1 A
0%
#445
b11 6
0!
13
b10 9
1%
#450
b1100100011001010111001101110000011011000110000101111010011000010110110101101001011001010110111001110100011011110010000001101001011011100110001101101111011100100111001001100101011000110111010001101111 =
b10 A
0%
#455
b0 6
b1111000 4
b1 2
0!
13
b11 9
1%
#460
b1100100011001010111001101110000011011000110000101111010011000010110110101101001011001010110111001110100011011110010000001101001011011100110001101101111011100100111001001100101011000110111010001101111 =
b11 A
0%
#465
b1 6
0!
13
b1111000 7
b0 9
b1 1
1%
#470
b1100100011001010111001101110000011011000110000101111010011000010110110101101001011001010110111001110100011011110010000001101001011011100110001101101111011100100111001001100101011000110111010001101111 =
b1 ?
b0 A
0%
#475
b10 6
0!
13
b1 9
1%
#480
b1100100011001010111001101110000011011000110000101111010011000010110110101101001011001010110111001110100011011110010000001101001011011100110001101101111011100100111001001100101011000110111010001101111 =
b1 A
0%
#485
b11 6
0!
13
b10 9
1%
#490
b1100100011001010111001101110000011011000110000101111010011000010110110101101001011001010110111001110100011011110010000001101001011011100110001101101111011100100111001001100101011000110111010001101111 =
b10 A
0%
#495
b0 6
b111100 4
b10 2
0!
13
b11 9
1%
#500
b1100100011001010111001101110000011011000110000101111010011000010110110101101001011001010110111001110100011011110010000001101001011011100110001101101111011100100111001001100101011000110111010001101111 =
b11 A
0%
#505
b1 6
0!
13
b111100 7
b0 9
b10 1
1%
#510
b1100100011001010111001101110000011011000110000101111010011000010110110101101001011001010110111001110100011011110010000001101001011011100110001101101111011100100111001001100101011000110111010001101111 =
b10 ?
b0 A
0%
#515
b10 6
0!
13
b1 9
1%
#520
b1100100011001010111001101110000011011000110000101111010011000010110110101101001011001010110111001110100011011110010000001101001011011100110001101101111011100100111001001100101011000110111010001101111 =
b1 A
0%
#525
b11 6
0!
13
b10 9
1%
#530
b1100100011001010111001101110000011011000110000101111010011000010110110101101001011001010110111001110100011011110010000001101001011011100110001101101111011100100111001001100101011000110111010001101111 =
b10 A
0%
#535
b0 6
b11110 4
b11 2
0!
13
b11 9
1%
#540
b1100100011001010111001101110000011011000110000101111010011000010110110101101001011001010110111001110100011011110010000001101001011011100110001101101111011100100111001001100101011000110111010001101111 =
b11 A
0%
#545
b1 6
0!
13
b11110 7
b0 9
b11 1
1%
#550
b1100100011001010111001101110000011011000110000101111010011000010110110101101001011001010110111001110100011011110010000001101001011011100110001101101111011100100111001001100101011000110111010001101111 =
b11 ?
b0 A
0%
#555
b10 6
0!
13
b1 9
1%
#560
b1100100011001010111001101110000011011000110000101111010011000010110110101101001011001010110111001110100011011110010000001101001011011100110001101101111011100100111001001100101011000110111010001101111 =
b1 A
0%
#565
b11 6
0!
13
b10 9
1%
#570
b1100100011001010111001101110000011011000110000101111010011000010110110101101001011001010110111001110100011011110010000001101001011011100110001101101111011100100111001001100101011000110111010001101111 =
b10 A
0%
#575
b0 6
b1111 4
b100 2
0!
13
b11 9
1%
#580
b1100100011001010111001101110000011011000110000101111010011000010110110101101001011001010110111001110100011011110010000001101001011011100110001101101111011100100111001001100101011000110111010001101111 =
b11 A
0%
#585
b1 6
1!
13
b1111 7
b0 9
b100 1
1%
#590
b10000 '
b1100100011001010111001101110000011011000110000101111010011000010110110101101001011001010110111001110100011011110010000001101001011011100110001101101111011100100111001001100101011000110111010001101111 =
b100 ?
b0 A
0%
#595
b10 6
13
b1 9
1%
#600
b1100100011001010111001101110000011011000110000101111010011000010110110101101001011001010110111001110100011011110010000001101001011011100110001101101111011100100111001001100101011000110111010001101111 =
b1 A
0%
#605
b11 6
13
b10 9
1%
#610
b1100100011001010111001101110000011011000110000101111010011000010110110101101001011001010110111001110100011011110010000001101001011011100110001101101111011100100111001001100101011000110111010001101111 =
b10 A
0%
#615
b0 6
b111 4
b101 2
13
b11 9
1%
#620
b1100100011001010111001101110000011011000110000101111010011000010110110101101001011001010110111001110100011011110010000001101001011011100110001101101111011100100111001001100101011000110111010001101111 =
b11 A
0%
#625
b1 6
13
b111 7
b0 9
b101 1
1%
#630
b110000 '
b1100100011001010111001101110000011011000110000101111010011000010110110101101001011001010110111001110100011011110010000001101001011011100110001101101111011100100111001001100101011000110111010001101111 =
b101 ?
b0 A
0%
#635
b10 6
13
b1 9
1%
#640
b1100100011001010111001101110000011011000110000101111010011000010110110101101001011001010110111001110100011011110010000001101001011011100110001101101111011100100111001001100101011000110111010001101111 =
b1 A
0%
#645
b11 6
13
b10 9
1%
#650
b1100100011001010111001101110000011011000110000101111010011000010110110101101001011001010110111001110100011011110010000001101001011011100110001101101111011100100111001001100101011000110111010001101111 =
b10 A
0%
#655
b0 6
b11 4
b110 2
13
b11 9
1%
#660
b1100100011001010111001101110000011011000110000101111010011000010110110101101001011001010110111001110100011011110010000001101001011011100110001101101111011100100111001001100101011000110111010001101111 =
b11 A
0%
#665
b1 6
13
b11 7
b0 9
b110 1
1%
#670
b1110000 '
b1100100011001010111001101110000011011000110000101111010011000010110110101101001011001010110111001110100011011110010000001101001011011100110001101101111011100100111001001100101011000110111010001101111 =
b110 ?
b0 A
0%
#675
b10 6
13
b1 9
1%
#680
b1100100011001010111001101110000011011000110000101111010011000010110110101101001011001010110111001110100011011110010000001101001011011100110001101101111011100100111001001100101011000110111010001101111 =
b1 A
0%
#685
b11 6
13
b10 9
1%
#690
b1100100011001010111001101110000011011000110000101111010011000010110110101101001011001010110111001110100011011110010000001101001011011100110001101101111011100100111001001100101011000110111010001101111 =
b10 A
0%
#695
b0 6
b1 4
b111 2
13
b11 9
1%
#700
b1100100011001010111001101110000011011000110000101111010011000010110110101101001011001010110111001110100011011110010000001101001011011100110001101101111011100100111001001100101011000110111010001101111 =
b11 A
0%
#705
b1 6
13
b1 7
b0 9
b111 1
1%
#710
b11110000 '
b1100100011001010111001101110000011011000110000101111010011000010110110101101001011001010110111001110100011011110010000001101001011011100110001101101111011100100111001001100101011000110111010001101111 =
b111 ?
b0 A
0%
#715
b10 6
13
b1 9
1%
#720
b1100100011001010111001101110000011011000110000101111010011000010110110101101001011001010110111001110100011011110010000001101001011011100110001101101111011100100111001001100101011000110111010001101111 =
b1 A
0%
#725
b11 6
13
b10 9
1%
#730
b1100100011001010111001101110000011011000110000101111010011000010110110101101001011001010110111001110100011011110010000001101001011011100110001101101111011100100111001001100101011000110111010001101111 =
b10 A
0%
#735
b11 5
03
b11 9
1%
#740
b1100100011001010111001101110000011011000110000101111010011000010110110101101001011001010110111001110100011011110010000001101001011011100110001101101111011100100111001001100101011000110111010001101111 =
b11 A
0%
#745
b0 5
1"
0#
b11 8
1%
#750
b1000100010011110100111001000101001000000110010001100101011000100110010100100000011000010110001101110100011010010111011001100001011100100010000001100100011011110110111001100101001000000111100100100000011001000110010101110011011000010110001101110100011010010111011001100001011100100010000001100010011101010111001101111001 =
b1000 ?
b100 A
0%
#755
0"
b0 8
1%
#760
b110010001101111011011100110010100100000011011100110111100100000011001000111010101110010011011110010000001110101011011100010000001100011011010010110001101101100011011110010000001101111001000000110001001110101011100110111100100100000011011100110111100100000011101100110111101101100011101100110100101101111001000000110000100100000011100100110010101110000011011110111001101101111 =
0%
#765
1%
#770
0%
#775
1%
#780
b1 :
b11 ;
b1 >
b11 @
0%
#785
1%
#790
13
b1 5
b0 '
1)
b1 &
b1 +
b11 *
b111001001100101011100000110111101110011011011110010000001101001011011100110001101101111011100100111001001100101011000110111010001101111 =
0%
#795
b10 5
b0 6
b0 2
13
1#
b1 8
1%
#800
b0 6
b0 2
13
b10 5
0)
b100110001001111010000010100010000100000011011110010000001100010011101010111001101111001001000000110100101101110011000110110111101110010011100100110010101100011011101000110111101110011 =
0%
#805
b1 6
13
b0 9
b0 1
b10 8
1%
#810
b1 '
b0 A
b0 ?
b1100100011001010111001101110000011011000110000101111010011000010110110101101001011001010110111001110100011011110010000001101001011011100110001101101111011100100111001001100101011000110111010001101111 =
0%
#815
b10 6
13
b1 9
1%
#820
b1100100011001010111001101110000011011000110000101111010011000010110110101101001011001010110111001110100011011110010000001101001011011100110001101101111011100100111001001100101011000110111010001101111 =
b1 A
0%
#825
b11 6
13
b10 9
1%
#830
b1100100011001010111001101110000011011000110000101111010011000010110110101101001011001010110111001110100011011110010000001101001011011100110001101101111011100100111001001100101011000110111010001101111 =
b10 A
0%
#835
b0 6
b0 4
b1 2
13
b11 9
1%
#840
b1100100011001010111001101110000011011000110000101111010011000010110110101101001011001010110111001110100011011110010000001101001011011100110001101101111011100100111001001100101011000110111010001101111 =
b11 A
0%
#845
b1 6
0!
13
b0 7
b0 9
b1 1
1%
#850
b1100100011001010111001101110000011011000110000101111010011000010110110101101001011001010110111001110100011011110010000001101001011011100110001101101111011100100111001001100101011000110111010001101111 =
b1 ?
b0 A
0%
#855
b10 6
0!
13
b1 9
1%
#860
b1100100011001010111001101110000011011000110000101111010011000010110110101101001011001010110111001110100011011110010000001101001011011100110001101101111011100100111001001100101011000110111010001101111 =
b1 A
0%
#865
b11 6
0!
13
b10 9
1%
#870
b1100100011001010111001101110000011011000110000101111010011000010110110101101001011001010110111001110100011011110010000001101001011011100110001101101111011100100111001001100101011000110111010001101111 =
b10 A
0%
#875
b0 6
b10 2
0!
13
b11 9
1%
#880
b1100100011001010111001101110000011011000110000101111010011000010110110101101001011001010110111001110100011011110010000001101001011011100110001101101111011100100111001001100101011000110111010001101111 =
b11 A
0%
#885
b1 6
0!
13
b0 9
b10 1
1%
#890
b1100100011001010111001101110000011011000110000101111010011000010110110101101001011001010110111001110100011011110010000001101001011011100110001101101111011100100111001001100101011000110111010001101111 =
b10 ?
b0 A
0%
#895
b10 6
0!
13
b1 9
1%
#900
b1100100011001010111001101110000011011000110000101111010011000010110110101101001011001010110111001110100011011110010000001101001011011100110001101101111011100100111001001100101011000110111010001101111 =
b1 A
0%
#905
b11 6
0!
13
b10 9
1%
#910
b1100100011001010111001101110000011011000110000101111010011000010110110101101001011001010110111001110100011011110010000001101001011011100110001101101111011100100111001001100101011000110111010001101111 =
b10 A
0%
#915
b0 6
b11 2
0!
13
b11 9
1%
#920
b1100100011001010111001101110000011011000110000101111010011000010110110101101001011001010110111001110100011011110010000001101001011011100110001101101111011100100111001001100101011000110111010001101111 =
b11 A
0%
#925
b1 6
0!
13
b0 9
b11 1
1%
#930
b1100100011001010111001101110000011011000110000101111010011000010110110101101001011001010110111001110100011011110010000001101001011011100110001101101111011100100111001001100101011000110111010001101111 =
b11 ?
b0 A
0%
#935
b10 6
0!
13
b1 9
1%
#940
b1100100011001010111001101110000011011000110000101111010011000010110110101101001011001010110111001110100011011110010000001101001011011100110001101101111011100100111001001100101011000110111010001101111 =
b1 A
0%
#945
b11 6
0!
13
b10 9
1%
