src/stoplight.v
`timescale 1ns/1ns

// Semaforo con la secuencia verde, amarillo, rojo y amarillo.
// Cada intervalo se mide en ciclos de reloj, no en tiempo real.
module stoplight(
    input clk,
    input rst,
    output red,
    output yellow,
    output green,
    output reg [2:0] counter
);

// state y counter guardan los valores actuales; next_* calcula los del proximo flanco.
reg [1:0] state, next_state;
reg [2:0] next_counter;

parameter S0 = 2'b00; // Verde durante 5 ciclos.
parameter S1 = 2'b01; // Amarillo antes de rojo, durante 2 ciclos.
parameter S2 = 2'b10; // Rojo durante 4 ciclos.
parameter S3 = 2'b11; // Amarillo antes de verde, durante 2 ciclos.

// El reset es asincrono: vuelve a verde sin esperar un flanco de reloj.
// En funcionamiento normal, ambos registros se actualizan al mismo tiempo.
always @(posedge clk or posedge rst) begin
    if (rst) begin
        state <= S0;
        counter <= 3'd0;
    end
    else begin
        state <= next_state;
        counter <= next_counter;
    end
end

// Por defecto se conserva el estado y se cuenta un ciclo mas.
// Al cambiar de luz se reinicia el contador para medir el nuevo intervalo.
always @(*) begin
    next_state = state;
    next_counter = counter + 3'd1;

    case (state)
        // El conteo empieza en cero: 0, 1, 2, 3 y 4 representan cinco ciclos.
        S0: begin
            if (counter == 3'd4) begin
                next_state = S1;
                next_counter = 3'd0;
            end
            else begin
                next_state = S0;
            end
        end
        S1: begin
            if (counter == 3'd1) begin
                next_state = S2;
                next_counter = 3'd0;
            end
            else begin
                next_state = S1;
            end
        end
        S2: begin
            if (counter == 3'd3) begin
                next_state = S3;
                next_counter = 3'd0;
            end
            else begin
                next_state = S2;
            end
        end
        // Este segundo amarillo recuerda que se viene de rojo y se debe ir a verde.
        S3: begin
            if (counter == 3'd1) begin
                next_state = S0;
                next_counter = 3'd0;
            end
            else begin
                next_state = S3;
            end
        end
        default begin
            next_state = S0;
            next_counter = 3'd0;
        end
    endcase
end

// Las luces dependen solo del estado actual. Los dos amarillos comparten salida,
// pero tienen destinos distintos; por eso se representan con estados separados.
assign red = (state == S2);
assign yellow = (state == S1) || (state == S3);
assign green = (state == S0);

endmodule

src/tb_stoplight.v
`timescale 1ns/1ns
`include "stoplight.v"
`timescale 1ns/1ns

// Comprueba la secuencia de luces, su duracion y el reset desde cada estado.
// Las tareas agrupan comprobaciones que se repiten durante la simulacion.
module tb_stoplight;
  reg clk, rst;
  wire red, yellow, green;
  wire [2:0] counter;
  // test_id identifica la prueba en GTKWave. Cada bit de reset_mask indica
  // si ya se probo el reset desde el estado del mismo numero.
  integer test_id, reset_mask;

  stoplight dut (
    .clk(clk), .rst(rst), .red(red), .yellow(yellow),
    .green(green), .counter(counter)
  );

  // Un cambio cada 5 ns produce un reloj de periodo 10 ns.
  initial clk = 0;
  always #5 clk = ~clk;

  // Una condicion falsa, desconocida (X) o flotante (Z) detiene la simulacion.
  // El mensaje permite localizar la prueba y el instante del fallo.
  task check;
    input condition;
    input [8*120-1:0] message;
    begin
      if (condition !== 1'b1)
        $fatal(1, "FAIL stoplight test=%0d t=%0t: %0s", test_id, $time, message);
    end
  endtask

  // Se observa en negedge, cuando las actualizaciones de posedge ya terminaron.
  task check_state;
    input [1:0] expected_state;
    input integer cycles;
    integer n;
    begin
      for (n = 0; n < cycles; n = n + 1) begin
        check(dut.state === expected_state, "estado o duracion incorrectos");
        check(counter === n[2:0], "contador incorrecto");
        check(green === (expected_state == 0), "green incorrecto");
        check(yellow === ((expected_state == 1) || (expected_state == 3)), "yellow incorrecto");
        check(red === (expected_state == 2), "red incorrecto");
        @(negedge clk);
      end
    end
  endtask

  // Se comprueban S0, S1, S2 y S3 con sus respectivas duraciones en ciclos.
  task full_sequence;
    begin
      check_state(2'd0, 5);
      check_state(2'd1, 2);
      check_state(2'd2, 4);
      check_state(2'd3, 2);
    end
  endtask

  // Espera el estado solicitado y verifica el retorno inmediato a verde.
  task reset_from_state;
    input [1:0] target;
    begin
      while (dut.state !== target) @(negedge clk);
      check(dut.state === target, "no se alcanzo el estado previo al reset");
      // Se activa entre flancos y se comprueba antes del siguiente flanco positivo.
      // Se desactiva en un flanco negativo para no coincidir con la actualizacion.
      #2 rst = 1;
      #1;
      check(dut.state === 2'd0 && counter === 3'd0, "reset asincrono incorrecto");
      check({green, yellow, red} === 3'b100, "salidas durante reset incorrectas");
      reset_mask = reset_mask | (1 << target);
      repeat (2) @(negedge clk);
      rst = 0;
      $display("OK stoplight reset desde S%0d, liberado t=%0t", target, $time);
    end
  endtask

  initial begin
    // Se guardan las señales del testbench y del modulo para revisarlas en GTKWave.
    $dumpfile("stoplight.vcd");
    $dumpvars(0, tb_stoplight);
    test_id = 0;
    reset_mask = 0;
    rst = 1;
    repeat (2) @(negedge clk);
    rst = 0;

    // Primero se verifica la operacion normal sin interrupciones.
    test_id = 1;
    full_sequence();
    full_sequence();
    $display("OK stoplight dos secuencias completas 5/2/4/2, t=%0t", $time);

    // Se cubren los cuatro estados de origen del reset.
    test_id = 2; reset_from_state(2'd0);
    test_id = 3; reset_from_state(2'd1);
    test_id = 4; reset_from_state(2'd2);
    test_id = 5; reset_from_state(2'd3);
    check(reset_mask == 15, "faltan estados en la cobertura de reset");

    // Se comprueba que el semaforo sigue funcionando despues de los resets.
    test_id = 6;
    full_sequence();
    $display("PASS stoplight: tiempos, luces y reset desde los cuatro estados");
    $finish;
  end

  initial begin
    // Evita una espera indefinida si el circuito no llega al estado esperado.
    #10000;
    $fatal(1, "Timeout stoplight");
  end
endmodule

src/stoplight.vcd
$date
	Sun Sep 20 13:31:39 2026
$end
$version
	Icarus Verilog
$end
$timescale
	1ns
$end
$scope module tb_stoplight $end
$var wire 1 ! yellow $end
$var wire 1 " red $end
$var wire 1 # green $end
$var wire 3 $ counter [2:0] $end
$var reg 1 % clk $end
$var reg 1 & rst $end
$var integer 32 ' reset_mask [31:0] $end
$var integer 32 ( test_id [31:0] $end
$scope module dut $end
$var wire 1 % clk $end
$var wire 1 & rst $end
$var wire 1 ! yellow $end
$var wire 1 " red $end
$var wire 1 # green $end
$var parameter 2 ) S0 $end
$var parameter 2 * S1 $end
$var parameter 2 + S2 $end
$var parameter 2 , S3 $end
$var reg 3 - counter [2:0] $end
$var reg 3 . next_counter [2:0] $end
$var reg 2 / next_state [1:0] $end
$var reg 2 0 state [1:0] $end
$upscope $end
$scope task check $end
$var reg 1 1 condition $end
$var reg 960 2 message [959:0] $end
$upscope $end
$scope task check_state $end
$var reg 2 3 expected_state [1:0] $end
$var integer 32 4 cycles [31:0] $end
$var integer 32 5 n [31:0] $end
$upscope $end
$scope task full_sequence $end
$upscope $end
$scope task reset_from_state $end
$var reg 2 6 target [1:0] $end
$upscope $end
$upscope $end
$enddefinitions $end
$comment Show the parameter values. $end
$dumpall
b11 ,
b10 +
b1 *
b0 )
$end
#0
$dumpvars
bx 6
bx 5
bx 4
bx 3
bx 2
x1
b0 0
b0 /
b1 .
b0 -
b0 (
b0 '
1&
0%
b0 $
1#
0"
0!
$end
#5
1%
#10
0%
#15
1%
#20
b111001001100101011001000010000001101001011011100110001101101111011100100111001001100101011000110111010001101111 2
11
b0 5
b101 4
b0 3
b1 (
0&
0%
#25
b10 .
b1 $
b1 -
1%
#30
b111001001100101011001000010000001101001011011100110001101101111011100100111001001100101011000110111010001101111 2
b1 5
0%
#35
b11 .
b10 $
b10 -
1%
#40
b111001001100101011001000010000001101001011011100110001101101111011100100111001001100101011000110111010001101111 2
b10 5
0%
#45
b100 .
b11 $
b11 -
1%
#50
b111001001100101011001000010000001101001011011100110001101101111011100100111001001100101011000110111010001101111 2
b11 5
0%
#55
b1 /
b0 .
b100 $
b100 -
1%
#60
b111001001100101011001000010000001101001011011100110001101101111011100100111001001100101011000110111010001101111 2
b100 5
0%
#65
b1 .
1!
b0 $
b0 -
0#
b1 0
1%
#70
b111001001100101011001000010000001101001011011100110001101101111011100100111001001100101011000110111010001101111 2
b10 4
b1 3
b0 5
0%
#75
b10 /
b0 .
b1 $
b1 -
1%
#80
b111001001100101011001000010000001101001011011100110001101101111011100100111001001100101011000110111010001101111 2
b1 5
0%
#85
b1 .
0!
b0 $
b0 -
1"
b10 0
1%
#90
b111001001100101011001000010000001101001011011100110001101101111011100100111001001100101011000110111010001101111 2
b100 4
b10 3
b0 5
0%
#95
b10 .
b1 $
b1 -
1%
#100
b111001001100101011001000010000001101001011011100110001101101111011100100111001001100101011000110111010001101111 2
b1 5
0%
#105
b11 .
b10 $
b10 -
1%
#110
b111001001100101011001000010000001101001011011100110001101101111011100100111001001100101011000110111010001101111 2
b10 5
0%
#115
b11 /
b0 .
b11 $
b11 -
1%
#120
b111001001100101011001000010000001101001011011100110001101101111011100100111001001100101011000110111010001101111 2
b11 5
0%
#125
b1 .
1!
b0 $
b0 -
0"
b11 0
1%
#130
b111001001100101011001000010000001101001011011100110001101101111011100100111001001100101011000110111010001101111 2
b10 4
b11 3
b0 5
0%
#135
b0 /
b0 .
b1 $
b1 -
1%
#140
b111001001100101011001000010000001101001011011100110001101101111011100100111001001100101011000110111010001101111 2
b1 5
0%
#145
b1 .
0!
b0 $
b0 -
1#
b0 0
1%
#150
b111001001100101011001000010000001101001011011100110001101101111011100100111001001100101011000110111010001101111 2
b101 4
b0 3
b0 5
0%
#155
b10 .
b1 $
b1 -
1%
#160
b111001001100101011001000010000001101001011011100110001101101111011100100111001001100101011000110111010001101111 2
b1 5
0%
#165
b11 .
b10 $
b10 -
1%
#170
b111001001100101011001000010000001101001011011100110001101101111011100100111001001100101011000110111010001101111 2
b10 5
0%
#175
b100 .
b11 $
b11 -
1%
#180
b111001001100101011001000010000001101001011011100110001101101111011100100111001001100101011000110111010001101111 2
b11 5
0%
#185
b1 /
b0 .
b100 $
b100 -
1%
#190
b111001001100101011001000010000001101001011011100110001101101111011100100111001001100101011000110111010001101111 2
b100 5
0%
#195
b1 .
1!
b0 $
b0 -
0#
b1 0
1%
#200
b111001001100101011001000010000001101001011011100110001101101111011100100111001001100101011000110111010001101111 2
b10 4
b1 3
b0 5
0%
#205
b10 /
b0 .
b1 $
b1 -
1%
#210
b111001001100101011001000010000001101001011011100110001101101111011100100111001001100101011000110111010001101111 2
b1 5
0%
#215
b1 .
0!
b0 $
b0 -
1"
b10 0
1%
#220
b111001001100101011001000010000001101001011011100110001101101111011100100111001001100101011000110111010001101111 2
b100 4
b10 3
b0 5
0%
#225
b10 .
b1 $
b1 -
1%
#230
b111001001100101011001000010000001101001011011100110001101101111011100100111001001100101011000110111010001101111 2
b1 5
0%
#235
b11 .
b10 $
b10 -
1%
#240
b111001001100101011001000010000001101001011011100110001101101111011100100111001001100101011000110111010001101111 2
b10 5
0%
#245
b11 /
b0 .
b11 $
b11 -
1%
#250
b111001001100101011001000010000001101001011011100110001101101111011100100111001001100101011000110111010001101111 2
b11 5
0%
#255
b1 .
1!
b0 $
b0 -
0"
b11 0
1%
#260
b111001001100101011001000010000001101001011011100110001101101111011100100111001001100101011000110111010001101111 2
b10 4
b11 3
b0 5
0%
#265
b0 /
b0 .
b1 $
b1 -
1%
#270
b111001001100101011001000010000001101001011011100110001101101111011100100111001001100101011000110111010001101111 2
b1 5
0%
#275
b1 .
0!
b0 $
b0 -
1#
b0 0
1%
#280
b11011100110111100100000011100110110010100100000011000010110110001100011011000010110111001111010011011110010000001100101011011000010000001100101011100110111010001100001011001000110111100100000011100000111001001100101011101100110100101101111001000000110000101101100001000000111001001100101011100110110010101110100 2
b0 6
b10 (
b10 5
0%
#282
1&
#283
b1 '
b11100110110000101101100011010010110010001100001011100110010000001100100011101010111001001100001011011100111010001100101001000000111001001100101011100110110010101110100001000000110100101101110011000110110111101110010011100100110010101100011011101000110000101110011 2
#285
1%
#290
0%
#295
1%
#300
b1 6
b11 (
0&
0%
#305
b10 .
b1 $
b1 -
1%
#310
0%
#315
b11 .
b10 $
b10 -
1%
#320
0%
#325
b100 .
b11 $
b11 -
1%
#330
0%
#335
b1 /
b0 .
b100 $
b100 -
1%
#340
0%
#345
b1 .
1!
b0 $
b0 -
0#
b1 0
1%
#350
b11011100110111100100000011100110110010100100000011000010110110001100011011000010110111001111010011011110010000001100101011011000010000001100101011100110111010001100001011001000110111100100000011100000111001001100101011101100110100101101111001000000110000101101100001000000111001001100101011100110110010101110100 2
0%
#352
b0 /
0!
1#
b0 0
1&
#353
b11 '
b11100110110000101101100011010010110010001100001011100110010000001100100011101010111001001100001011011100111010001100101001000000111001001100101011100110110010101110100001000000110100101101110011000110110111101110010011100100110010101100011011101000110000101110011 2
#355
1%
#360
0%
#365
1%
#370
b10 6
b100 (
0&
0%
#375
b10 .
b1 $
b1 -
1%
#380
0%
#385
b11 .
b10 $
b10 -
1%
#390
0%
#395
b100 .
b11 $
b11 -
1%
#400
0%
#405
b1 /
b0 .
b100 $
b100 -
1%
#410
0%
#415
b1 .
1!
b0 $
b0 -
0#
b1 0
1%
#420
0%
#425
b10 /
b0 .
b1 $
b1 -
1%
#430
0%
#435
b1 .
0!
b0 $
b0 -
1"
b10 0
1%
#440
b11011100110111100100000011100110110010100100000011000010110110001100011011000010110111001111010011011110010000001100101011011000010000001100101011100110111010001100001011001000110111100100000011100000111001001100101011101100110100101101111001000000110000101101100001000000111001001100101011100110110010101110100 2
0%
#442
b0 /
0"
1#
b0 0
1&
#443
b111 '
b11100110110000101101100011010010110010001100001011100110010000001100100011101010111001001100001011011100111010001100101001000000111001001100101011100110110010101110100001000000110100101101110011000110110111101110010011100100110010101100011011101000110000101110011 2
#445
1%
#450
0%
#455
1%
#460
b11 6
b101 (
0&
0%
#465
b10 .
b1 $
b1 -
1%
#470
0%
#475
b11 .
b10 $
b10 -
1%
#480
0%
#485
b100 .
b11 $
b11 -
1%
#490
0%
#495
b1 /
b0 .
b100 $
b100 -
1%
#500
0%
#505
b1 .
1!
b0 $
b0 -
0#
b1 0
1%
#510
0%
#515
b10 /
b0 .
b1 $
b1 -
1%
#520
0%
#525
b1 .
0!
b0 $
b0 -
1"
b10 0
1%
#530
0%
#535
b10 .
b1 $
b1 -
1%
#540
0%
#545
b11 .
b10 $
b10 -
1%
#550
0%
#555
b11 /
b0 .
b11 $
b11 -
1%
#560
0%
#565
b1 .
1!
b0 $
b0 -
0"
b11 0
1%
#570
b11011100110111100100000011100110110010100100000011000010110110001100011011000010110111001111010011011110010000001100101011011000010000001100101011100110111010001100001011001000110111100100000011100000111001001100101011101100110100101101111001000000110000101101100001000000111001001100101011100110110010101110100 2
0%
#572
b0 /
0!
1#
b0 0
1&
#573
b1111 '
b11100110110000101101100011010010110010001100001011100110010000001100100011101010111001001100001011011100111010001100101001000000111001001100101011100110110010101110100001000000110100101101110011000110110111101110010011100100110010101100011011101000110000101110011 2
#575
1%
#580
0%
#585
1%
#590
b0 5
b101 4
b0 3
b110 (
b111001001100101011001000010000001101001011011100110001101101111011100100111001001100101011000110111010001101111 2
0&
0%
#595
b10 .
b1 $
b1 -
1%
#600
b111001001100101011001000010000001101001011011100110001101101111011100100111001001100101011000110111010001101111 2
b1 5
0%
#605
b11 .
b10 $
b10 -
1%
#610
b111001001100101011001000010000001101001011011100110001101101111011100100111001001100101011000110111010001101111 2
b10 5
0%
#615
b100 .
b11 $
b11 -
1%
#620
b111001001100101011001000010000001101001011011100110001101101111011100100111001001100101011000110111010001101111 2
b11 5
0%
#625
b1 /
b0 .
b100 $
b100 -
1%
#630
b111001001100101011001000010000001101001011011100110001101101111011100100111001001100101011000110111010001101111 2
b100 5
0%
#635
b1 .
1!
b0 $
b0 -
0#
b1 0
1%
#640
b111001001100101011001000010000001101001011011100110001101101111011100100111001001100101011000110111010001101111 2
b10 4
b1 3
b0 5
0%
#645
b10 /
b0 .
b1 $
b1 -
1%
#650
b111001001100101011001000010000001101001011011100110001101101111011100100111001001100101011000110111010001101111 2
b1 5
0%
#655
b1 .
0!
b0 $
b0 -
1"
b10 0
1%
#660
b111001001100101011001000010000001101001011011100110001101101111011100100111001001100101011000110111010001101111 2
b100 4
b10 3
b0 5
0%
#665
b10 .
b1 $
b1 -
1%
#670
b111001001100101011001000010000001101001011011100110001101101111011100100111001001100101011000110111010001101111 2
b1 5
0%
#675
b11 .
b10 $
b10 -
1%
#680
b111001001100101011001000010000001101001011011100110001101101111011100100111001001100101011000110111010001101111 2
b10 5
0%
#685
b11 /
b0 .
b11 $
b11 -
1%
#690
b111001001100101011001000010000001101001011011100110001101101111011100100111001001100101011000110111010001101111 2
b11 5
0%
#695
b1 .
1!
b0 $
b0 -
0"
b11 0
1%
#700
b111001001100101011001000010000001101001011011100110001101101111011100100111001001100101011000110111010001101111 2
b10 4
b11 3
b0 5
0%
#705
b0 /
b0 .
b1 $
b1 -
1%
#710
b111001001100101011001000010000001101001011011100110001101101111011100100111001001100101011000110111010001101111 2
b1 5
0%
#715
b1 .
0!
b0 $
b0 -
1#
b0 0
1%
#720
b10 5
0%
